Workbook
Name IQ_CH: 110000
Name IQ_CQ: 5000
Name IQ_CY: 10000
Name IQ_DAILY: 500000
Name IQ_FH: 100000
Name IQ_FQ: 500
Name IQ_FY: 1000
Name IQ_LTM: 2000
Name IQ_MONTH: 15000
Name IQ_NTM: 6000
Name IQ_WEEK: 50000
Name IQ_YTD: 3000

Sheet Table of Contents
A1: Table of Contents
A2: Directions to Use This Model/File
A3: Note that the best way to use this file is to turn off automatic calculations in excel (Formulas tab-->Calculation Options-->Manual). When adjusting the Monte Carlo Inputs, use the "Calculate Now" button to run all 5,000 simulations. Note, this may take a moment. For best results, let your fingers rest while the model is calculating.
A5: Tab | B5: Description | C5: Uses
A6: Tesla Valuation Inputs | B6: This tab has all of our input variables for our Monte Carlo analysis, including a range for each variable. These inputs feed directly into our Monte Carlo Single Simulation tab, and to the price and adoption tables from the Valuation ASP Tables tab, which then feed into the Monte Carlo Single Simulation tab. Here, we also calculate the bull, bear, and expected value from the Monte Carlo Simulation Output tab. | C6: Can change the range of inputs for a monte carlo valuation of Tesla and view how it changes the Bull, Bear, and Expected values.
A7: Valuation ASP Tables | B7: This tab has our tables for Tesla's average vehicle selling price, price per mile for ride-hail service, and ride-hail adoption curve. These tables feed into the Monte Carlo Single Simulation tab. | C7: Can change the average selling price assumptions for the Tesla Valuation.
A8: Monte Carlo Single Simulation | B8: This tab takes the variables from our Tesla Valuation Inputs tab and calculates single simulation runs using values within the ranges we laid out for each variable. | C8: View a single simulation of the monte carlo valuation.
A9: Monte Carlo Simulation Output | B9: This tab is an output of 5,000 simulation runs of our Monte Carlo. We have highlighted some key outputs from the model in each column. | C9: View simulation outputs after you change Monte Carlo Inputs.

Sheet ARK Disclosure
A2: This work is licensed under a Creative Commons Attribution-Non-Commercial 4.0 International License.
A3: You may not use the material for commercial purposes without first obtaining written permission.
A5: 2025, ARK Investment Management LLC. All content is original and has been researched and produced by ARK Investment Management LLC (“ARK”) unless otherwise stated herein.
A7: In this tool, you can investigate the assumptions, criteria and methodology used in this Monte Carlo simulation to determine the value of a single security in future years. A Monte Carlo simulation is intended to assist in understanding the impact of risk and uncertainty in forecasting or predicting a future event. The simulation works by assigning multiple values to a set of variables to achieve multiple results, and then averaging those results to obtain an estimate; here, this simulation is being used to predict the price of a single security in future years. The tool is inherently limited by its nature, including the assumption of perfectly efficient markets. ARK has used its research to determine what it believes are reasonable ranges for variables modelled as well as which business lines will have the biggest determination on the security’s future value. The tool is designed to forecast the price of a single security over time. Please refer to the blog for additional information on the assumptions, criteria and methodology used, and the limitations of this tool. The results may vary with each use and over time. This tool relies on historical information of the modelled security, including publicly available financial data sources, and analysis of that data by ARK and by third-parties, combined with ARK’s research to forecast over a future time horizon. Please note that key inputs are included in the Tesla Valuation Inputs tab of this GitHub document. The reader is urged to use extreme caution when considering the forecasted performance, as it is inherently subjective and reflects ARK’s long term positive view of the company. There is no guarantee that any results will align with the forecasted performance, and they might not be predictive. This tool is intended to analyze a single security, and we note that other companies were not considered that may have characteristics similar or superior to those being analyzed. This tool generates outcomes that are hypothetical in nature.
A9: The forecasts and price estimates herein are subject to revision by ARK Invest (“ARK”) and provided solely as a guide to current expectations. Forecasts regarding broad markets and individual issuers are not, and are not intended to be, representative of any ARK-managed investment product or the characteristics of any ARK portfolio.
A11: FORECASTS ARE HYPOTHETICAL AND HIGHLY SPECULATIVE, AND PRESENT MANY RISKS AND LIMITATIONS. While ARK believes that there is a sound basis for the forecasts presented, they are provided for illustrative purposes only and no representations are made as to their accuracy.
A13: This material is intended only to provide observations and views of the author(s) at the time of writing, both of which are subject to change at any time without prior notice. Certain of the statements contained herein are statements of future expectations and other forward-looking statements that are based on ARK's current views and assumptions and involve known and unknown risks and uncertainties that could cause actual results, performance or events to differ materially from those expressed or implied in such statements. Past performance is no guarantee of future results. Equities may decline in value due to both real and perceived general market, economic, and industry conditions.
A15: ARK does not have investment banking, consulting, or any type of fee-paying relationship with the subject company.

Sheet Tesla Valuation Inputs
A1: Tesla Valuation Inputs
A2: Blue text indicates assumptions that can be altered; altering one input may require altering another input in order to get reasonable results. | B2: Current Price | C2: 2031 Expected Value | D2: Bear | E2: Bull | F2: CAGR | G2: Notes:
A3: Black text indicates cells with formulas or cells with static values that are not meant to be altered. | B3: 354.72 | C3: =AVERAGE('Monte Carlo Simulation Output'!Q6:Q5005) -> 4341.5216 | D3: =QUARTILE('Monte Carlo Simulation Output'!Q6:Q5005,1) -> 3308.9775 | E3: =QUARTILE('Monte Carlo Simulation Output'!Q6:Q5005,3) -> 5052.5564 | F3: =(C3/B3)^(1/F4)-1 -> 0.61712644 | G3: Note that occasionally simulation will produce an error when certain variables grow extremely large in very rare scenarios. Re-run simulation in this case and error will likely disappear.
A4: Note: To utilize the Monte Carlo, you need to use the "Calculate Now" button in excel, not "Calculate Sheet". | B4: Dates | C4: 46311 | D4: 48213 | F4: =(D4-C4)/365 -> 5.2109589 | G4: Please also note that each simulation run contains variance that may cause the bull, bear and expected values to differ in between runs.
A5: Values are in millions unless otherwise specified except for per share amounts, multiples, and ratios.
A9: Key Drivers | B9: Minimum | C9: Downside | D9: Upside | E9: Maximum | G9: MC Input | H9: Random Number Generator | I9: Median
A10: Max annual vehicle production increase (given management bandwidth constraints) | B10: 0.2 | C10: 0.35 | D10: 0.45 | E10: 0.6 | G10: =IF(I10=D10,I10,IF(_xlfn.NORM.INV(H10,I10,(D10-I10))<B10,B10,IF(_xlfn.NORM.INV(H10,I10,(D10-I10))>E10,E10,_xlfn.NORM.INV(H10,I10,(D10-I10))))) -> 0.40507328 | H10: =RAND() -> 0.54040953 | I10: =('Tesla Valuation Inputs'!D10-'Tesla Valuation Inputs'!C10)/2+'Tesla Valuation Inputs'!C10 -> 0.4
A11: Miles traveled per robotaxi (not in millions) | B11: 30000 | C11: 55000 | D11: 75000 | E11: 100000 | G11: =IF(I11=D11,I11,IF(_xlfn.NORM.INV(H11,I11,(D11-I11))<B11,B11,IF(_xlfn.NORM.INV(H11,I11,(D11-I11))>E11,E11,_xlfn.NORM.INV(H11,I11,(D11-I11))))) -> 74200.303 | H11: =RAND() -> 0.82122155 | I11: =('Tesla Valuation Inputs'!D11-'Tesla Valuation Inputs'!C11)/2+'Tesla Valuation Inputs'!C11 -> 65000
A12: Takeover time for autonomous adoption (years between 10% and 90% market saturation) | B12: 2 | C12: 3 | D12: 9 | E12: 15 | G12: =IF(I12=D12,I12,IF(_xlfn.NORM.INV(H12,I12,(D12-I12))<B12,B12,IF(_xlfn.NORM.INV(H12,I12,(D12-I12))>E12,E12,_xlfn.NORM.INV(H12,I12,(D12-I12))))) -> 5.2343191 | H12: =RAND() -> 0.3992739 | I12: =('Tesla Valuation Inputs'!D12-'Tesla Valuation Inputs'!C12)/2+'Tesla Valuation Inputs'!C12 -> 6
A13: Max annual Optimi production increase (given management bandwidth constraints) | B13: 1.5 | C13: 2.5 | D13: 3 | E13: 5 | G13: =IF(I13=D13,I13,IF(_xlfn.NORM.INV(H13,I13,(D13-I13))<B13,B13,IF(_xlfn.NORM.INV(H13,I13,(D13-I13))>E13,E13,_xlfn.NORM.INV(H13,I13,(D13-I13))))) -> 2.6548271 | H13: =RAND() -> 0.351716 | I13: =('Tesla Valuation Inputs'!D13-'Tesla Valuation Inputs'!C13)/2+'Tesla Valuation Inputs'!C13 -> 2.75
A14: Balance sheet assumptions | B14: Minimum | C14: Downside | D14: Upside | E14: Maximum
A15: Percent of factory-build/internal fleet that will be debt funded | B15: 0 | C15: 0.1 | D15: 0.15 | E15: 0.2 | G15: =IF(I15=D15,I15,IF(_xlfn.NORM.INV(H15,I15,(D15-I15))<B15,B15,IF(_xlfn.NORM.INV(H15,I15,(D15-I15))>E15,E15,_xlfn.NORM.INV(H15,I15,(D15-I15))))) -> 0.15850238 | H15: =RAND() -> 0.90989281 | I15: =('Tesla Valuation Inputs'!D15-'Tesla Valuation Inputs'!C15)/2+'Tesla Valuation Inputs'!C15 -> 0.125
A16: Vehicle capital efficiency 2031 (gross capex per vehicle produced, not in millions) | B16: 2000 | C16: 5000 | D16: 7000 | E16: 14000 | G16: =IF(I16=D16,I16,IF(_xlfn.NORM.INV(H16,I16,(D16-I16))<B16,B16,IF(_xlfn.NORM.INV(H16,I16,(D16-I16))>E16,E16,_xlfn.NORM.INV(H16,I16,(D16-I16))))) -> 6348.8086 | H16: =RAND() -> 0.6363835 | I16: =('Tesla Valuation Inputs'!D16-'Tesla Valuation Inputs'!C16)/2+'Tesla Valuation Inputs'!C16 -> 6000
A17: % of Year-end cash that's dedicated to AI Infrastructure and Chip Development | B17: 0.1 | C17: 0.15 | D17: 0.2 | E17: 0.25 | G17: =IF(I17=D17,I17,IF(_xlfn.NORM.INV(H17,I17,(D17-I17))<B17,B17,IF(_xlfn.NORM.INV(H17,I17,(D17-I17))>E17,E17,_xlfn.NORM.INV(H17,I17,(D17-I17))))) -> 0.14541062 | H17: =RAND() -> 0.11829064 | I17: =('Tesla Valuation Inputs'!D17-'Tesla Valuation Inputs'!C17)/2+'Tesla Valuation Inputs'!C17 -> 0.175
A18: Bitcoin price appreciation (depreciation) annual | B18: -0.5 | C18: -0.3 | D18: 0.5 | E18: 1 | G18: =IF(I18=D18,I18,IF(_xlfn.NORM.INV(H18,I18,(D18-I18))<B18,B18,IF(_xlfn.NORM.INV(H18,I18,(D18-I18))>E18,E18,_xlfn.NORM.INV(H18,I18,(D18-I18))))) -> -0.12771641 | H18: =RAND() -> 0.28457932 | I18: =('Tesla Valuation Inputs'!D18-'Tesla Valuation Inputs'!C18)/2+'Tesla Valuation Inputs'!C18 -> 0.1
A19: Weighted average market capitalization at which equity is raised (millions) | B19: 700000 | C19: 1000000 | D19: 2000000 | E19: 3000000 | G19: =IF(I19=D19,I19,IF(_xlfn.NORM.INV(H19,I19,(D19-I19))<B19,B19,IF(_xlfn.NORM.INV(H19,I19,(D19-I19))>E19,E19,_xlfn.NORM.INV(H19,I19,(D19-I19))))) -> 1846881.4 | H19: =RAND() -> 0.75608454 | I19: =('Tesla Valuation Inputs'!D19-'Tesla Valuation Inputs'!C19)/2+'Tesla Valuation Inputs'!C19 -> 1500000
A20: Equity raise for capex (millions) | B20: 0 | C20: 0 | D20: 0 | E20: 0 | G20: =IF(I20=D20,I20,IF(_xlfn.NORM.INV(H20,I20,(D20-I20))<B20,B20,IF(_xlfn.NORM.INV(H20,I20,(D20-I20))>E20,E20,_xlfn.NORM.INV(H20,I20,(D20-I20))))) -> 0 | H20: =RAND() -> 0.88060379 | I20: =('Tesla Valuation Inputs'!D20-'Tesla Valuation Inputs'!C20)/2+'Tesla Valuation Inputs'!C20 -> 0
A21: Margin Assumptions | B21: Minimum | C21: Downside | D21: Upside | E21: Maximum
A22: Max gross margin on vehicle sales | B22: 0.125 | C22: 0.2 | D22: 0.3 | E22: 0.5 | G22: =IF(I22=D22,I22,IF(_xlfn.NORM.INV(H22,I22,(D22-I22))<B22,B22,IF(_xlfn.NORM.INV(H22,I22,(D22-I22))>E22,E22,_xlfn.NORM.INV(H22,I22,(D22-I22))))) -> 0.28066579 | H22: =RAND() -> 0.73016622 | I22: =('Tesla Valuation Inputs'!D22-'Tesla Valuation Inputs'!C22)/2+'Tesla Valuation Inputs'!C22 -> 0.25
A23: Wright's Law learning rate | B23: 0.1 | C23: 0.14 | D23: 0.17 | E23: 0.2 | F23: For more on Wright's Law, see: https://ark-invest.com/wrights-law/ | G23: =IF(I23=D23,I23,IF(_xlfn.NORM.INV(H23,I23,(D23-I23))<B23,B23,IF(_xlfn.NORM.INV(H23,I23,(D23-I23))>E23,E23,_xlfn.NORM.INV(H23,I23,(D23-I23))))) -> 0.16553012 | H23: =RAND() -> 0.758663 | I23: =('Tesla Valuation Inputs'!D23-'Tesla Valuation Inputs'!C23)/2+'Tesla Valuation Inputs'!C23 -> 0.155
A24: Electric Vehicle factory utilization factor | B24: 0.7 | C24: 0.7 | D24: 0.9 | E24: 0.95 | G24: =IF(I24=D24,I24,IF(_xlfn.NORM.INV(H24,I24,(D24-I24))<B24,B24,IF(_xlfn.NORM.INV(H24,I24,(D24-I24))>E24,E24,_xlfn.NORM.INV(H24,I24,(D24-I24))))) -> 0.7 | H24: =RAND() -> 0.031964554 | I24: =('Tesla Valuation Inputs'!D24-'Tesla Valuation Inputs'!C24)/2+'Tesla Valuation Inputs'!C24 -> 0.8
A25: Percent of each model/price segment that Tesla penetrates | B25: 0.05 | C25: 0.075 | D25: 0.125 | E25: 0.2 | G25: =IF(I25=D25,I25,IF(_xlfn.NORM.INV(H25,I25,(D25-I25))<B25,B25,IF(_xlfn.NORM.INV(H25,I25,(D25-I25))>E25,E25,_xlfn.NORM.INV(H25,I25,(D25-I25))))) -> 0.068013237 | H25: =RAND() -> 0.1003657 | I25: =('Tesla Valuation Inputs'!D25-'Tesla Valuation Inputs'!C25)/2+'Tesla Valuation Inputs'!C25 -> 0.1
A26: Tax rate | B26: 0.15 | C26: 0.175 | D26: 0.225 | E26: 0.25 | G26: =IF(I26=D26,I26,IF(_xlfn.NORM.INV(H26,I26,(D26-I26))<B26,B26,IF(_xlfn.NORM.INV(H26,I26,(D26-I26))>E26,E26,_xlfn.NORM.INV(H26,I26,(D26-I26))))) -> 0.21258129 | H26: =RAND() -> 0.69260628 | I26: =('Tesla Valuation Inputs'!D26-'Tesla Valuation Inputs'!C26)/2+'Tesla Valuation Inputs'!C26 -> 0.2
A27: Interest rate | B27: 0.02 | C27: 0.04 | D27: 0.06 | E27: 0.06 | G27: =IF(I27=D27,I27,IF(_xlfn.NORM.INV(H27,I27,(D27-I27))<B27,B27,IF(_xlfn.NORM.INV(H27,I27,(D27-I27))>E27,E27,_xlfn.NORM.INV(H27,I27,(D27-I27))))) -> 0.034487119 | H27: =RAND() -> 0.060416326 | I27: =('Tesla Valuation Inputs'!D27-'Tesla Valuation Inputs'!C27)/2+'Tesla Valuation Inputs'!C27 -> 0.05
A28: EBITDA As A % of Gross Margin - Electric Vehicle | B28: 0.6 | C28: 0.65 | D28: 0.75 | E28: 0.8 | G28: =IF(I28=D28,I28,IF(_xlfn.NORM.INV(H28,I28,(D28-I28))<B28,B28,IF(_xlfn.NORM.INV(H28,I28,(D28-I28))>E28,E28,_xlfn.NORM.INV(H28,I28,(D28-I28))))) -> 0.77597188 | H28: =RAND() -> 0.93567381 | I28: =('Tesla Valuation Inputs'!D28-'Tesla Valuation Inputs'!C28)/2+'Tesla Valuation Inputs'!C28 -> 0.7
A29: EBITDA As A % of Gross Margin - Stationary Energy Storage | B29: 0.65 | C29: 0.675 | D29: 0.775 | E29: 0.8 | G29: =IF(I29=D29,I29,IF(_xlfn.NORM.INV(H29,I29,(D29-I29))<B29,B29,IF(_xlfn.NORM.INV(H29,I29,(D29-I29))>E29,E29,_xlfn.NORM.INV(H29,I29,(D29-I29))))) -> 0.70984475 | H29: =RAND() -> 0.38090494 | I29: =('Tesla Valuation Inputs'!D29-'Tesla Valuation Inputs'!C29)/2+'Tesla Valuation Inputs'!C29 -> 0.725
A30: EBITDA As A % of Gross Margin - Optimus Hardware Sales | B30: 0.7 | C30: 0.7 | D30: 0.8 | E30: 0.8 | G30: =IF(I30=D30,I30,IF(_xlfn.NORM.INV(H30,I30,(D30-I30))<B30,B30,IF(_xlfn.NORM.INV(H30,I30,(D30-I30))>E30,E30,_xlfn.NORM.INV(H30,I30,(D30-I30))))) -> 0.8 | H30: =RAND() -> 0.86727881 | I30: =('Tesla Valuation Inputs'!D30-'Tesla Valuation Inputs'!C30)/2+'Tesla Valuation Inputs'!C30 -> 0.75
A31: EBITDA As A % of Gross Margin - Optimus RaaS | B31: 0.7 | C31: 0.75 | D31: 0.85 | E31: 0.9 | G31: =IF(I31=D31,I31,IF(_xlfn.NORM.INV(H31,I31,(D31-I31))<B31,B31,IF(_xlfn.NORM.INV(H31,I31,(D31-I31))>E31,E31,_xlfn.NORM.INV(H31,I31,(D31-I31))))) -> 0.79953231 | H31: =RAND() -> 0.4962684 | I31: =('Tesla Valuation Inputs'!D31-'Tesla Valuation Inputs'!C31)/2+'Tesla Valuation Inputs'!C31 -> 0.8
A32: Autonomous Assumptions | B32: Minimum | C32: Downside | D32: Upside | E32: Maximum
A33: Percent of customer owned fleet in China | B33: 0.2 | C33: 0.3 | D33: 0.4 | E33: 0.5 | G33: =IF(I33=D33,I33,IF(_xlfn.NORM.INV(H33,I33,(D33-I33))<B33,B33,IF(_xlfn.NORM.INV(H33,I33,(D33-I33))>E33,E33,_xlfn.NORM.INV(H33,I33,(D33-I33))))) -> 0.37694604 | H33: =RAND() -> 0.70502927 | I33: =('Tesla Valuation Inputs'!D33-'Tesla Valuation Inputs'!C33)/2+'Tesla Valuation Inputs'!C33 -> 0.35
A34: Maximum robotaxis Tesla will own & operate itself (not in millions) | B34: 2000 | C34: 3000 | D34: 4000 | E34: 5000 | G34: =IF(I34=D34,I34,IF(_xlfn.NORM.INV(H34,I34,(D34-I34))<B34,B34,IF(_xlfn.NORM.INV(H34,I34,(D34-I34))>E34,E34,_xlfn.NORM.INV(H34,I34,(D34-I34))))) -> 3443.1085 | H34: =RAND() -> 0.45470494 | I34: =('Tesla Valuation Inputs'!D34-'Tesla Valuation Inputs'!C34)/2+'Tesla Valuation Inputs'!C34 -> 3500
A35: Stationary Energy Storage Assumptions | B35: Minimum | C35: Downside | D35: Upside | E35: Maximum
A36: Stationary energy storage capital efficiency 2031 (gross capex per MWh deployed, not in millions) | B36: 5000 | C36: 6000 | D36: 8000 | E36: 10000 | G36: =IF(I36=D36,I36,IF(_xlfn.NORM.INV(H36,I36,(D36-I36))<B36,B36,IF(_xlfn.NORM.INV(H36,I36,(D36-I36))>E36,E36,_xlfn.NORM.INV(H36,I36,(D36-I36))))) -> 7981.6733 | H36: =RAND() -> 0.8368696 | I36: =('Tesla Valuation Inputs'!D36-'Tesla Valuation Inputs'!C36)/2+'Tesla Valuation Inputs'!C36 -> 7000
A37: Max annual energy increase (given management bandwidth constraints) | B37: 0.4 | C37: 0.8 | D37: 1 | E37: 1.2 | G37: =IF(I37=D37,I37,IF(_xlfn.NORM.INV(H37,I37,(D37-I37))<B37,B37,IF(_xlfn.NORM.INV(H37,I37,(D37-I37))>E37,E37,_xlfn.NORM.INV(H37,I37,(D37-I37))))) -> 0.98115305 | H37: =RAND() -> 0.79146947 | I37: =('Tesla Valuation Inputs'!D37-'Tesla Valuation Inputs'!C37)/2+'Tesla Valuation Inputs'!C37 -> 0.9
A38: Gross margin of stationary energy storage business in 2031 | B38: 0.1 | C38: 0.2 | D38: 0.3 | E38: 0.4 | G38: =IF(I38=D38,I38,IF(_xlfn.NORM.INV(H38,I38,(D38-I38))<B38,B38,IF(_xlfn.NORM.INV(H38,I38,(D38-I38))>E38,E38,_xlfn.NORM.INV(H38,I38,(D38-I38))))) -> 0.24214251 | H38: =RAND() -> 0.43756337 | I38: =('Tesla Valuation Inputs'!D38-'Tesla Valuation Inputs'!C38)/2+'Tesla Valuation Inputs'!C38 -> 0.25
A39: Optimus Assumptions | B39: Minimum | C39: Downside | D39: Upside | E39: Maximum
A40: Optimus Capability Increase For Every Cumulative Doubling in AI Spend | B40: 0.05 | C40: 0.1 | D40: 0.15 | E40: 0.2 | G40: =IF(I40=D40,I40,IF(_xlfn.NORM.INV(H40,I40,(D40-I40))<B40,B40,IF(_xlfn.NORM.INV(H40,I40,(D40-I40))>E40,E40,_xlfn.NORM.INV(H40,I40,(D40-I40))))) -> 0.10423006 | H40: =RAND() -> 0.203044 | I40: =('Tesla Valuation Inputs'!D40-'Tesla Valuation Inputs'!C40)/2+'Tesla Valuation Inputs'!C40 -> 0.125
A41: What year does Tesla begin selling Optimi externally? | B41: 2027 | C41: 2027 | D41: 2029 | E41: 2030 | G41: =ROUND(IF(I41=D41,I41,IF(_xlfn.NORM.INV(H41,I41,(D41-I41))<B41,B41,IF(_xlfn.NORM.INV(H41,I41,(D41-I41))>E41,E41,_xlfn.NORM.INV(H41,I41,(D41-I41))))),0) -> 2029 | H41: =RAND() -> 0.82819471 | I41: =('Tesla Valuation Inputs'!D41-'Tesla Valuation Inputs'!C41)/2+'Tesla Valuation Inputs'!C41 -> 2028
A42: Once available for external use - what % of Optimi production does Tesla dedicate to in-house use up until the cap is reached? | B42: 0 | C42: 0.05 | D42: 0.1 | E42: 0.2 | G42: =IF(I42=D42,I42,IF(_xlfn.NORM.INV(H42,I42,(D42-I42))<B42,B42,IF(_xlfn.NORM.INV(H42,I42,(D42-I42))>E42,E42,_xlfn.NORM.INV(H42,I42,(D42-I42))))) -> 0.03430329 | H42: =RAND() -> 0.051776398 | I42: =('Tesla Valuation Inputs'!D42-'Tesla Valuation Inputs'!C42)/2+'Tesla Valuation Inputs'!C42 -> 0.075
A43: Maximum Optimi deployed in the factory | B43: 13500 | C43: 67500 | D43: 135000 | E43: 270000 | G43: =IF(I43=D43,I43,IF(_xlfn.NORM.INV(H43,I43,(D43-I43))<B43,B43,IF(_xlfn.NORM.INV(H43,I43,(D43-I43))>E43,E43,_xlfn.NORM.INV(H43,I43,(D43-I43))))) -> 75885.943 | H43: =RAND() -> 0.22616759 | I43: =('Tesla Valuation Inputs'!D43-'Tesla Valuation Inputs'!C43)/2+'Tesla Valuation Inputs'!C43 -> 101250
A44: Optimi capital efficiency 2031 (gross capex per Optimi produced, not in millions) | B44: 500 | C44: 6000 | D44: 8000 | E44: 20000 | G44: =IF(I44=D44,I44,IF(_xlfn.NORM.INV(H44,I44,(D44-I44))<B44,B44,IF(_xlfn.NORM.INV(H44,I44,(D44-I44))>E44,E44,_xlfn.NORM.INV(H44,I44,(D44-I44))))) -> 6708.2128 | H44: =RAND() -> 0.38522466 | I44: =('Tesla Valuation Inputs'!D44-'Tesla Valuation Inputs'!C44)/2+'Tesla Valuation Inputs'!C44 -> 7000
A45: Optimi Hardware Gross Margin | B45: 0.125 | C45: 0.3 | D45: 0.35 | E45: 0.4 | G45: =IF(I45=D45,I45,IF(_xlfn.NORM.INV(H45,I45,(D45-I45))<B45,B45,IF(_xlfn.NORM.INV(H45,I45,(D45-I45))>E45,E45,_xlfn.NORM.INV(H45,I45,(D45-I45))))) -> 0.34876011 | H45: =RAND() -> 0.82904658 | I45: =('Tesla Valuation Inputs'!D45-'Tesla Valuation Inputs'!C45)/2+'Tesla Valuation Inputs'!C45 -> 0.325
A46: RaaS Gross Margin (software subscription margin) | B46: 0.7 | C46: 0.7 | D46: 0.8 | E46: 0.9 | G46: =IF(I46=D46,I46,IF(_xlfn.NORM.INV(H46,I46,(D46-I46))<B46,B46,IF(_xlfn.NORM.INV(H46,I46,(D46-I46))>E46,E46,_xlfn.NORM.INV(H46,I46,(D46-I46))))) -> 0.76046081 | H46: =RAND() -> 0.58286029 | I46: =('Tesla Valuation Inputs'!D46-'Tesla Valuation Inputs'!C46)/2+'Tesla Valuation Inputs'!C46 -> 0.75

Sheet Valuation ASP Tables
A1: Valuation ASP Tables
A2: Blue text indicates assumptions that can be altered, altering one input may require altering another input in order to get reasonable results
A3: Black text indicates cells with formulas or cells with static values that are not meant to be altered
A5: Electric Vehicle ASP Table
A6: Model | B6: Global ASP | C6: TAM units in segment | D6: Max units Tesla | E6: Cumulative units | F6: Market Segments | G6: Cumulative Market Size At Each Segment | H6: Notes
A7: Micromobility EV | B7: 7000 | C7: 1000000000000 | D7: =$C7*'Monte Carlo Single Simulation'!$N$25 -> 6.8013237e+10 | E7: =D7+E8 -> 6.8025402e+10 | F7: =B7*D7 -> 4.7609266e+14 | G7: =F7+G8 -> 4.7639284e+14 | H7: Note, top bucket is nominally large to prevent formula error in rare scenarios.
A8: Neighborhood EV | B8: 15000 | C8: 100000000 | D8: =$C8*'Monte Carlo Single Simulation'!$N$25 -> 6801323.7 | E8: =D8+E9 -> 12165363 | F8: =B8*D8 -> 1.0201985e+11 | G8: =F8+G9 -> 3.0018291e+11
A9: Cybercab | B9: 25000 | C9: 41000000 | D9: =$C9*'Monte Carlo Single Simulation'!$N$25 -> 2788542.7 | E9: =D9+E10 -> 5364039.1 | F9: =B9*D9 -> 6.9713568e+10 | G9: =F9+G10 -> 1.9816306e+11
A10: Cybertruck | B10: 80000 | C10: 1500000 | D10: =$C10*'Monte Carlo Single Simulation'!$N$25 -> 102019.85 | E10: =D10+E11 -> 2575496.4 | F10: =B10*D10 -> 8.1615884e+09 | G10: =F10+G11 -> 1.2844949e+11
A11: Model Y | B11: 50000 | C11: 22000000 | D11: =$C11*'Monte Carlo Single Simulation'!$N$25 -> 1496291.2 | E11: =D11+E12 -> 2473476.5 | F11: =B11*D11 -> 7.481456e+10 | G11: =F11+G12 -> 1.202879e+11
A12: Model 3 | B12: 45000 | C12: 14000000 | D12: =$C12*'Monte Carlo Single Simulation'!$N$25 -> 952185.31 | E12: =D12+E13 -> 977185.31 | F12: =B12*D12 -> 4.2848339e+10 | G12: =F12+G13 -> 4.5473339e+10
A13: S/X | B13: 105000 | C13: 25000 | D13: 25000 | E13: =D13 -> 25000 | F13: =B13*D13 -> 2625000000 | G13: =F13 -> 2625000000 | H13: Model S/X hardcoded to roughly match 2026 sales; retired from 2027 onwards (excluded from the ASP calculation).
A15: Graph Inputs | C15: Note: This adoption curve is used to assign eligible cars to the robotaxi fleet.
A16: Base Year | B16: 0
A17: Saturation Percentage | B17: 100
A18: Start of Fast Growth | B18: 3
A19: Take Over Time | B19: ='Monte Carlo Single Simulation'!N12 -> 5.2343191
A21: Year | B21: Penetration
A22: 0 | B22: =$B$17/(1+POWER(81,($B$18+$B$19/2-A22)/$B$19))*(1/100) -> 0.0088727235
A23: =A22+1 -> 1 | B23: =$B$17/(1+POWER(81,($B$18+$B$19/2-A23)/$B$19))*(1/100) -> 0.020306164
A24: =A23+1 -> 2 | B24: =$B$17/(1+POWER(81,($B$18+$B$19/2-A24)/$B$19))*(1/100) -> 0.045792095
A25: =A24+1 -> 3 | B25: =$B$17/(1+POWER(81,($B$18+$B$19/2-A25)/$B$19))*(1/100) -> 0.1
A26: =A25+1 -> 4 | B26: =$B$17/(1+POWER(81,($B$18+$B$19/2-A26)/$B$19))*(1/100) -> 0.20461778
A27: =A26+1 -> 5 | B27: =$B$17/(1+POWER(81,($B$18+$B$19/2-A27)/$B$19))*(1/100) -> 0.37328878
A28: =A27+1 -> 6 | B28: =$B$17/(1+POWER(81,($B$18+$B$19/2-A28)/$B$19))*(1/100) -> 0.57966833
A29: =A28+1 -> 7 | B29: =$B$17/(1+POWER(81,($B$18+$B$19/2-A29)/$B$19))*(1/100) -> 0.76150666
A30: =A29+1 -> 8 | B30: =$B$17/(1+POWER(81,($B$18+$B$19/2-A30)/$B$19))*(1/100) -> 0.88084989
A31: =A30+1 -> 9 | B31: =$B$17/(1+POWER(81,($B$18+$B$19/2-A31)/$B$19))*(1/100) -> 0.944802
A32: =A31+1 -> 10 | B32: =$B$17/(1+POWER(81,($B$18+$B$19/2-A32)/$B$19))*(1/100) -> 0.97538783
A33: =A32+1 -> 11 | B33: =$B$17/(1+POWER(81,($B$18+$B$19/2-A33)/$B$19))*(1/100) -> 0.9892191
A34: =A33+1 -> 12 | B34: =$B$17/(1+POWER(81,($B$18+$B$19/2-A34)/$B$19))*(1/100) -> 0.99531496
... A37: =A36+1 -> 15 | B37: =$B$17/(1+POWER(81,($B$18+$B$19/2-A37)/$B$19))*(1/100) -> 0.9996209
A40: Note the lowest price mileage bucket is inflated to catch any overfall in cases of extreme growth within the Monte Carlo
A41: Ride-hail ASP Table | L41: Decile Inputs (constant across all years) | P41: Cost Inputs by Year ($/mi, constant across deciles)
A42: Year | B42: Price Decile | C42: Metro Miles | D42: Cumulative Metro Miles | E42: Price Per Mile | F42: Price Market Segments | G42: Cumulative Price Market Size | H42: Fleet Owner Fee | I42: Platform Operator COGS | J42: Platform Operator Overhead | L42: Price Decile | M42: Cohort Miles (bn) | N42: Cohort Price $/mi | P42: Year | Q42: Fleet Owner Fee | R42: Platform Operator COGS | S42: Platform Operator OH
A43: {=INDEX($P$43:$P$57,INT((ROW()-43)/10)+1)} -> 2026 | B43: {=INDEX($L$43:$L$52,MOD(ROW()-43,10)+1)} -> D1 | C43: =_xlfn.XLOOKUP($B43,$L$43:$L$52,$M$43:$M$52)*10^9 -> 200000000000000 | D43: =C43+D44 -> 202371100000000 | E43: =_xlfn.XLOOKUP($B43,$L$43:$L$52,$N$43:$N$52) -> 0.443 | F43: =C43*E43 -> 88600000000000 | G43: =F43+G44 -> 91099582600000 | H43: =_xlfn.XLOOKUP($A43,$P$43:$P$57,$Q$43:$Q$57) -> 0.33168904 | I43: =_xlfn.XLOOKUP($A43,$P$43:$P$57,$R$43:$R$57) -> 0.24 | J43: =_xlfn.XLOOKUP($A43,$P$43:$P$57,$S$43:$S$57) -> 0.11 | L43: D1 | M43: 200000 | N43: 0.443 | O43: Note, D1 bucket is overflow to prevent formulae error. | P43: 2026 | Q43: 0.33168904 | R43: 0.24 | S43: 0.11
A44: {=INDEX($P$43:$P$57,INT((ROW()-43)/10)+1)} -> 2026 | B44: {=INDEX($L$43:$L$52,MOD(ROW()-43,10)+1)} -> D2 | C44: =_xlfn.XLOOKUP($B44,$L$43:$L$52,$M$43:$M$52)*10^9 -> 186000000000 | D44: =C44+D45 -> 2371100000000 | E44: =_xlfn.XLOOKUP($B44,$L$43:$L$52,$N$43:$N$52) -> 0.537 | F44: =C44*E44 -> 99882000000 | G44: =F44+G45 -> 2499582600000 | H44: =_xlfn.XLOOKUP($A44,$P$43:$P$57,$Q$43:$Q$57) -> 0.33168904 | I44: =_xlfn.XLOOKUP($A44,$P$43:$P$57,$R$43:$R$57) -> 0.24 | J44: =_xlfn.XLOOKUP($A44,$P$43:$P$57,$S$43:$S$57) -> 0.11 | L44: D2 | M44: 186 | N44: 0.537 | P44: 2027 | Q44: 0.21610846 | R44: 0.16 | S44: 0.09
A45: {=INDEX($P$43:$P$57,INT((ROW()-43)/10)+1)} -> 2026 | B45: {=INDEX($L$43:$L$52,MOD(ROW()-43,10)+1)} -> D3 | C45: =_xlfn.XLOOKUP($B45,$L$43:$L$52,$M$43:$M$52)*10^9 -> 205000000000 | D45: =C45+D46 -> 2185100000000 | E45: =_xlfn.XLOOKUP($B45,$L$43:$L$52,$N$43:$N$52) -> 0.624 | F45: =C45*E45 -> 127920000000 | G45: =F45+G46 -> 2399700600000 | H45: =_xlfn.XLOOKUP($A45,$P$43:$P$57,$Q$43:$Q$57) -> 0.33168904 | I45: =_xlfn.XLOOKUP($A45,$P$43:$P$57,$R$43:$R$57) -> 0.24 | J45: =_xlfn.XLOOKUP($A45,$P$43:$P$57,$S$43:$S$57) -> 0.11 | L45: D3 | M45: 205 | N45: 0.624 | P45: 2028 | Q45: 0.19701344 | R45: 0.11 | S45: 0.08
A46: {=INDEX($P$43:$P$57,INT((ROW()-43)/10)+1)} -> 2026 | B46: {=INDEX($L$43:$L$52,MOD(ROW()-43,10)+1)} -> D4 | C46: =_xlfn.XLOOKUP($B46,$L$43:$L$52,$M$43:$M$52)*10^9 -> 219300000000 | D46: =C46+D47 -> 1980100000000 | E46: =_xlfn.XLOOKUP($B46,$L$43:$L$52,$N$43:$N$52) -> 0.699 | F46: =C46*E46 -> 153290700000 | G46: =F46+G47 -> 2271780600000 | H46: =_xlfn.XLOOKUP($A46,$P$43:$P$57,$Q$43:$Q$57) -> 0.33168904 | I46: =_xlfn.XLOOKUP($A46,$P$43:$P$57,$R$43:$R$57) -> 0.24 | J46: =_xlfn.XLOOKUP($A46,$P$43:$P$57,$S$43:$S$57) -> 0.11 | L46: D4 | M46: 219.3 | N46: 0.699 | P46: 2029 | Q46: 0.1903348 | R46: 0.07 | S46: 0.07
A47: {=INDEX($P$43:$P$57,INT((ROW()-43)/10)+1)} -> 2026 | B47: {=INDEX($L$43:$L$52,MOD(ROW()-43,10)+1)} -> D5 | C47: =_xlfn.XLOOKUP($B47,$L$43:$L$52,$M$43:$M$52)*10^9 -> 238500000000 | D47: =C47+D48 -> 1760800000000 | E47: =_xlfn.XLOOKUP($B47,$L$43:$L$52,$N$43:$N$52) -> 0.798 | F47: =C47*E47 -> 190323000000 | G47: =F47+G48 -> 2118489900000 | H47: =_xlfn.XLOOKUP($A47,$P$43:$P$57,$Q$43:$Q$57) -> 0.33168904 | I47: =_xlfn.XLOOKUP($A47,$P$43:$P$57,$R$43:$R$57) -> 0.24 | J47: =_xlfn.XLOOKUP($A47,$P$43:$P$57,$S$43:$S$57) -> 0.11 | L47: D5 | M47: 238.5 | N47: 0.798 | P47: 2030 | Q47: 0.18544418 | R47: 0.06 | S47: 0.06
A48: {=INDEX($P$43:$P$57,INT((ROW()-43)/10)+1)} -> 2026 | B48: {=INDEX($L$43:$L$52,MOD(ROW()-43,10)+1)} -> D6 | C48: =_xlfn.XLOOKUP($B48,$L$43:$L$52,$M$43:$M$52)*10^9 -> 257300000000 | D48: =C48+D49 -> 1522300000000 | E48: =_xlfn.XLOOKUP($B48,$L$43:$L$52,$N$43:$N$52) -> 0.858 | F48: =C48*E48 -> 220763400000 | G48: =F48+G49 -> 1928166900000 | H48: =_xlfn.XLOOKUP($A48,$P$43:$P$57,$Q$43:$Q$57) -> 0.33168904 | I48: =_xlfn.XLOOKUP($A48,$P$43:$P$57,$R$43:$R$57) -> 0.24 | J48: =_xlfn.XLOOKUP($A48,$P$43:$P$57,$S$43:$S$57) -> 0.11 | L48: D6 | M48: 257.3 | N48: 0.858 | P48: 2031 | Q48: 0.18176245 | R48: 0.04 | S48: 0.06
A49: {=INDEX($P$43:$P$57,INT((ROW()-43)/10)+1)} -> 2026 | B49: {=INDEX($L$43:$L$52,MOD(ROW()-43,10)+1)} -> D7 | C49: =_xlfn.XLOOKUP($B49,$L$43:$L$52,$M$43:$M$52)*10^9 -> 278500000000 | D49: =C49+D50 -> 1265000000000 | E49: =_xlfn.XLOOKUP($B49,$L$43:$L$52,$N$43:$N$52) -> 0.99 | F49: =C49*E49 -> 275715000000 | G49: =F49+G50 -> 1707403500000 | H49: =_xlfn.XLOOKUP($A49,$P$43:$P$57,$Q$43:$Q$57) -> 0.33168904 | I49: =_xlfn.XLOOKUP($A49,$P$43:$P$57,$R$43:$R$57) -> 0.24 | J49: =_xlfn.XLOOKUP($A49,$P$43:$P$57,$S$43:$S$57) -> 0.11 | L49: D7 | M49: 278.5 | N49: 0.99 | P49: 2032 | Q49: 0.17893265 | R49: 0.04 | S49: 0.06
A50: {=INDEX($P$43:$P$57,INT((ROW()-43)/10)+1)} -> 2026 | B50: {=INDEX($L$43:$L$52,MOD(ROW()-43,10)+1)} -> D8 | C50: =_xlfn.XLOOKUP($B50,$L$43:$L$52,$M$43:$M$52)*10^9 -> 736500000000 | D50: =C50+D51 -> 986500000000 | E50: =_xlfn.XLOOKUP($B50,$L$43:$L$52,$N$43:$N$52) -> 1.249 | F50: =C50*E50 -> 9.198885e+11 | G50: =F50+G51 -> 1431688500000 | H50: =_xlfn.XLOOKUP($A50,$P$43:$P$57,$Q$43:$Q$57) -> 0.33168904 | I50: =_xlfn.XLOOKUP($A50,$P$43:$P$57,$R$43:$R$57) -> 0.24 | J50: =_xlfn.XLOOKUP($A50,$P$43:$P$57,$S$43:$S$57) -> 0.11 | L50: D8 | M50: 736.5 | N50: 1.249 | P50: 2033 | Q50: 0.17893265 | R50: 0.04 | S50: 0.06
A51: {=INDEX($P$43:$P$57,INT((ROW()-43)/10)+1)} -> 2026 | B51: {=INDEX($L$43:$L$52,MOD(ROW()-43,10)+1)} -> D9 | C51: =_xlfn.XLOOKUP($B51,$L$43:$L$52,$M$43:$M$52)*10^9 -> 150000000000 | D51: =C51+D52 -> 250000000000 | E51: =_xlfn.XLOOKUP($B51,$L$43:$L$52,$N$43:$N$52) -> 1.58 | F51: =C51*E51 -> 237000000000 | G51: =F51+G52 -> 511800000000 | H51: =_xlfn.XLOOKUP($A51,$P$43:$P$57,$Q$43:$Q$57) -> 0.33168904 | I51: =_xlfn.XLOOKUP($A51,$P$43:$P$57,$R$43:$R$57) -> 0.24 | J51: =_xlfn.XLOOKUP($A51,$P$43:$P$57,$S$43:$S$57) -> 0.11 | L51: D9 | M51: 150 | N51: 1.58 | P51: 2034 | Q51: 0.17893265 | R51: 0.04 | S51: 0.06
A52: {=INDEX($P$43:$P$57,INT((ROW()-43)/10)+1)} -> 2026 | B52: {=INDEX($L$43:$L$52,MOD(ROW()-43,10)+1)} -> D10 | C52: =_xlfn.XLOOKUP($B52,$L$43:$L$52,$M$43:$M$52)*10^9 -> 100000000000 | D52: =C52 -> 100000000000 | E52: =_xlfn.XLOOKUP($B52,$L$43:$L$52,$N$43:$N$52) -> 2.748 | F52: =C52*E52 -> 2.748e+11 | G52: =F52 -> 2.748e+11 | H52: =_xlfn.XLOOKUP($A52,$P$43:$P$57,$Q$43:$Q$57) -> 0.33168904 | I52: =_xlfn.XLOOKUP($A52,$P$43:$P$57,$R$43:$R$57) -> 0.24 | J52: =_xlfn.XLOOKUP($A52,$P$43:$P$57,$S$43:$S$57) -> 0.11 | L52: D10 | M52: 100 | N52: 2.748 | P52: 2035 | Q52: 0.17893265 | R52: 0.04 | S52: 0.06
A53: {=INDEX($P$43:$P$57,INT((ROW()-43)/10)+1)} -> 2027 | B53: {=INDEX($L$43:$L$52,MOD(ROW()-43,10)+1)} -> D1 | C53: =_xlfn.XLOOKUP($B53,$L$43:$L$52,$M$43:$M$52)*10^9 -> 200000000000000 | D53: =C53+D54 -> 202371100000000 | E53: =_xlfn.XLOOKUP($B53,$L$43:$L$52,$N$43:$N$52) -> 0.443 | F53: =C53*E53 -> 88600000000000 | G53: =F53+G54 -> 91099582600000 | H53: =_xlfn.XLOOKUP($A53,$P$43:$P$57,$Q$43:$Q$57) -> 0.21610846 | I53: =_xlfn.XLOOKUP($A53,$P$43:$P$57,$R$43:$R$57) -> 0.16 | J53: =_xlfn.XLOOKUP($A53,$P$43:$P$57,$S$43:$S$57) -> 0.09 | P53: 2036 | Q53: 0.17893265 | R53: 0.04 | S53: 0.06
A54: {=INDEX($P$43:$P$57,INT((ROW()-43)/10)+1)} -> 2027 | B54: {=INDEX($L$43:$L$52,MOD(ROW()-43,10)+1)} -> D2 | C54: =_xlfn.XLOOKUP($B54,$L$43:$L$52,$M$43:$M$52)*10^9 -> 186000000000 | D54: =C54+D55 -> 2371100000000 | E54: =_xlfn.XLOOKUP($B54,$L$43:$L$52,$N$43:$N$52) -> 0.537 | F54: =C54*E54 -> 99882000000 | G54: =F54+G55 -> 2499582600000 | H54: =_xlfn.XLOOKUP($A54,$P$43:$P$57,$Q$43:$Q$57) -> 0.21610846 | I54: =_xlfn.XLOOKUP($A54,$P$43:$P$57,$R$43:$R$57) -> 0.16 | J54: =_xlfn.XLOOKUP($A54,$P$43:$P$57,$S$43:$S$57) -> 0.09 | P54: 2037 | Q54: 0.17893265 | R54: 0.04 | S54: 0.06
A55: {=INDEX($P$43:$P$57,INT((ROW()-43)/10)+1)} -> 2027 | B55: {=INDEX($L$43:$L$52,MOD(ROW()-43,10)+1)} -> D3 | C55: =_xlfn.XLOOKUP($B55,$L$43:$L$52,$M$43:$M$52)*10^9 -> 205000000000 | D55: =C55+D56 -> 2185100000000 | E55: =_xlfn.XLOOKUP($B55,$L$43:$L$52,$N$43:$N$52) -> 0.624 | F55: =C55*E55 -> 127920000000 | G55: =F55+G56 -> 2399700600000 | H55: =_xlfn.XLOOKUP($A55,$P$43:$P$57,$Q$43:$Q$57) -> 0.21610846 | I55: =_xlfn.XLOOKUP($A55,$P$43:$P$57,$R$43:$R$57) -> 0.16 | J55: =_xlfn.XLOOKUP($A55,$P$43:$P$57,$S$43:$S$57) -> 0.09 | P55: 2038 | Q55: 0.17893265 | R55: 0.04 | S55: 0.06
A56: {=INDEX($P$43:$P$57,INT((ROW()-43)/10)+1)} -> 2027 | B56: {=INDEX($L$43:$L$52,MOD(ROW()-43,10)+1)} -> D4 | C56: =_xlfn.XLOOKUP($B56,$L$43:$L$52,$M$43:$M$52)*10^9 -> 219300000000 | D56: =C56+D57 -> 1980100000000 | E56: =_xlfn.XLOOKUP($B56,$L$43:$L$52,$N$43:$N$52) -> 0.699 | F56: =C56*E56 -> 153290700000 | G56: =F56+G57 -> 2271780600000 | H56: =_xlfn.XLOOKUP($A56,$P$43:$P$57,$Q$43:$Q$57) -> 0.21610846 | I56: =_xlfn.XLOOKUP($A56,$P$43:$P$57,$R$43:$R$57) -> 0.16 | J56: =_xlfn.XLOOKUP($A56,$P$43:$P$57,$S$43:$S$57) -> 0.09 | P56: 2039 | Q56: 0.17893265 | R56: 0.04 | S56: 0.06
A57: {=INDEX($P$43:$P$57,INT((ROW()-43)/10)+1)} -> 2027 | B57: {=INDEX($L$43:$L$52,MOD(ROW()-43,10)+1)} -> D5 | C57: =_xlfn.XLOOKUP($B57,$L$43:$L$52,$M$43:$M$52)*10^9 -> 238500000000 | D57: =C57+D58 -> 1760800000000 | E57: =_xlfn.XLOOKUP($B57,$L$43:$L$52,$N$43:$N$52) -> 0.798 | F57: =C57*E57 -> 190323000000 | G57: =F57+G58 -> 2118489900000 | H57: =_xlfn.XLOOKUP($A57,$P$43:$P$57,$Q$43:$Q$57) -> 0.21610846 | I57: =_xlfn.XLOOKUP($A57,$P$43:$P$57,$R$43:$R$57) -> 0.16 | J57: =_xlfn.XLOOKUP($A57,$P$43:$P$57,$S$43:$S$57) -> 0.09 | P57: 2040 | Q57: 0.17893265 | R57: 0.04 | S57: 0.06
A58: {=INDEX($P$43:$P$57,INT((ROW()-43)/10)+1)} -> 2027 | B58: {=INDEX($L$43:$L$52,MOD(ROW()-43,10)+1)} -> D6 | C58: =_xlfn.XLOOKUP($B58,$L$43:$L$52,$M$43:$M$52)*10^9 -> 257300000000 | D58: =C58+D59 -> 1522300000000 | E58: =_xlfn.XLOOKUP($B58,$L$43:$L$52,$N$43:$N$52) -> 0.858 | F58: =C58*E58 -> 220763400000 | G58: =F58+G59 -> 1928166900000 | H58: =_xlfn.XLOOKUP($A58,$P$43:$P$57,$Q$43:$Q$57) -> 0.21610846 | I58: =_xlfn.XLOOKUP($A58,$P$43:$P$57,$R$43:$R$57) -> 0.16 | J58: =_xlfn.XLOOKUP($A58,$P$43:$P$57,$S$43:$S$57) -> 0.09
A59: {=INDEX($P$43:$P$57,INT((ROW()-43)/10)+1)} -> 2027 | B59: {=INDEX($L$43:$L$52,MOD(ROW()-43,10)+1)} -> D7 | C59: =_xlfn.XLOOKUP($B59,$L$43:$L$52,$M$43:$M$52)*10^9 -> 278500000000 | D59: =C59+D60 -> 1265000000000 | E59: =_xlfn.XLOOKUP($B59,$L$43:$L$52,$N$43:$N$52) -> 0.99 | F59: =C59*E59 -> 275715000000 | G59: =F59+G60 -> 1707403500000 | H59: =_xlfn.XLOOKUP($A59,$P$43:$P$57,$Q$43:$Q$57) -> 0.21610846 | I59: =_xlfn.XLOOKUP($A59,$P$43:$P$57,$R$43:$R$57) -> 0.16 | J59: =_xlfn.XLOOKUP($A59,$P$43:$P$57,$S$43:$S$57) -> 0.09
A60: {=INDEX($P$43:$P$57,INT((ROW()-43)/10)+1)} -> 2027 | B60: {=INDEX($L$43:$L$52,MOD(ROW()-43,10)+1)} -> D8 | C60: =_xlfn.XLOOKUP($B60,$L$43:$L$52,$M$43:$M$52)*10^9 -> 736500000000 | D60: =C60+D61 -> 986500000000 | E60: =_xlfn.XLOOKUP($B60,$L$43:$L$52,$N$43:$N$52) -> 1.249 | F60: =C60*E60 -> 9.198885e+11 | G60: =F60+G61 -> 1431688500000 | H60: =_xlfn.XLOOKUP($A60,$P$43:$P$57,$Q$43:$Q$57) -> 0.21610846 | I60: =_xlfn.XLOOKUP($A60,$P$43:$P$57,$R$43:$R$57) -> 0.16 | J60: =_xlfn.XLOOKUP($A60,$P$43:$P$57,$S$43:$S$57) -> 0.09
A61: {=INDEX($P$43:$P$57,INT((ROW()-43)/10)+1)} -> 2027 | B61: {=INDEX($L$43:$L$52,MOD(ROW()-43,10)+1)} -> D9 | C61: =_xlfn.XLOOKUP($B61,$L$43:$L$52,$M$43:$M$52)*10^9 -> 150000000000 | D61: =C61+D62 -> 250000000000 | E61: =_xlfn.XLOOKUP($B61,$L$43:$L$52,$N$43:$N$52) -> 1.58 | F61: =C61*E61 -> 237000000000 | G61: =F61+G62 -> 511800000000 | H61: =_xlfn.XLOOKUP($A61,$P$43:$P$57,$Q$43:$Q$57) -> 0.21610846 | I61: =_xlfn.XLOOKUP($A61,$P$43:$P$57,$R$43:$R$57) -> 0.16 | J61: =_xlfn.XLOOKUP($A61,$P$43:$P$57,$S$43:$S$57) -> 0.09
A62: {=INDEX($P$43:$P$57,INT((ROW()-43)/10)+1)} -> 2027 | B62: {=INDEX($L$43:$L$52,MOD(ROW()-43,10)+1)} -> D10 | C62: =_xlfn.XLOOKUP($B62,$L$43:$L$52,$M$43:$M$52)*10^9 -> 100000000000 | D62: =C62 -> 100000000000 | E62: =_xlfn.XLOOKUP($B62,$L$43:$L$52,$N$43:$N$52) -> 2.748 | F62: =C62*E62 -> 2.748e+11 | G62: =F62 -> 2.748e+11 | H62: =_xlfn.XLOOKUP($A62,$P$43:$P$57,$Q$43:$Q$57) -> 0.21610846 | I62: =_xlfn.XLOOKUP($A62,$P$43:$P$57,$R$43:$R$57) -> 0.16 | J62: =_xlfn.XLOOKUP($A62,$P$43:$P$57,$S$43:$S$57) -> 0.09
A63: {=INDEX($P$43:$P$57,INT((ROW()-43)/10)+1)} -> 2028 | B63: {=INDEX($L$43:$L$52,MOD(ROW()-43,10)+1)} -> D1 | C63: =_xlfn.XLOOKUP($B63,$L$43:$L$52,$M$43:$M$52)*10^9 -> 200000000000000 | D63: =C63+D64 -> 202371100000000 | E63: =_xlfn.XLOOKUP($B63,$L$43:$L$52,$N$43:$N$52) -> 0.443 | F63: =C63*E63 -> 88600000000000 | G63: =F63+G64 -> 91099582600000 | H63: =_xlfn.XLOOKUP($A63,$P$43:$P$57,$Q$43:$Q$57) -> 0.19701344 | I63: =_xlfn.XLOOKUP($A63,$P$43:$P$57,$R$43:$R$57) -> 0.11 | J63: =_xlfn.XLOOKUP($A63,$P$43:$P$57,$S$43:$S$57) -> 0.08
A64: {=INDEX($P$43:$P$57,INT((ROW()-43)/10)+1)} -> 2028 | B64: {=INDEX($L$43:$L$52,MOD(ROW()-43,10)+1)} -> D2 | C64: =_xlfn.XLOOKUP($B64,$L$43:$L$52,$M$43:$M$52)*10^9 -> 186000000000 | D64: =C64+D65 -> 2371100000000 | E64: =_xlfn.XLOOKUP($B64,$L$43:$L$52,$N$43:$N$52) -> 0.537 | F64: =C64*E64 -> 99882000000 | G64: =F64+G65 -> 2499582600000 | H64: =_xlfn.XLOOKUP($A64,$P$43:$P$57,$Q$43:$Q$57) -> 0.19701344 | I64: =_xlfn.XLOOKUP($A64,$P$43:$P$57,$R$43:$R$57) -> 0.11 | J64: =_xlfn.XLOOKUP($A64,$P$43:$P$57,$S$43:$S$57) -> 0.08
A65: {=INDEX($P$43:$P$57,INT((ROW()-43)/10)+1)} -> 2028 | B65: {=INDEX($L$43:$L$52,MOD(ROW()-43,10)+1)} -> D3 | C65: =_xlfn.XLOOKUP($B65,$L$43:$L$52,$M$43:$M$52)*10^9 -> 205000000000 | D65: =C65+D66 -> 2185100000000 | E65: =_xlfn.XLOOKUP($B65,$L$43:$L$52,$N$43:$N$52) -> 0.624 | F65: =C65*E65 -> 127920000000 | G65: =F65+G66 -> 2399700600000 | H65: =_xlfn.XLOOKUP($A65,$P$43:$P$57,$Q$43:$Q$57) -> 0.19701344 | I65: =_xlfn.XLOOKUP($A65,$P$43:$P$57,$R$43:$R$57) -> 0.11 | J65: =_xlfn.XLOOKUP($A65,$P$43:$P$57,$S$43:$S$57) -> 0.08
A66: {=INDEX($P$43:$P$57,INT((ROW()-43)/10)+1)} -> 2028 | B66: {=INDEX($L$43:$L$52,MOD(ROW()-43,10)+1)} -> D4 | C66: =_xlfn.XLOOKUP($B66,$L$43:$L$52,$M$43:$M$52)*10^9 -> 219300000000 | D66: =C66+D67 -> 1980100000000 | E66: =_xlfn.XLOOKUP($B66,$L$43:$L$52,$N$43:$N$52) -> 0.699 | F66: =C66*E66 -> 153290700000 | G66: =F66+G67 -> 2271780600000 | H66: =_xlfn.XLOOKUP($A66,$P$43:$P$57,$Q$43:$Q$57) -> 0.19701344 | I66: =_xlfn.XLOOKUP($A66,$P$43:$P$57,$R$43:$R$57) -> 0.11 | J66: =_xlfn.XLOOKUP($A66,$P$43:$P$57,$S$43:$S$57) -> 0.08
A67: {=INDEX($P$43:$P$57,INT((ROW()-43)/10)+1)} -> 2028 | B67: {=INDEX($L$43:$L$52,MOD(ROW()-43,10)+1)} -> D5 | C67: =_xlfn.XLOOKUP($B67,$L$43:$L$52,$M$43:$M$52)*10^9 -> 238500000000 | D67: =C67+D68 -> 1760800000000 | E67: =_xlfn.XLOOKUP($B67,$L$43:$L$52,$N$43:$N$52) -> 0.798 | F67: =C67*E67 -> 190323000000 | G67: =F67+G68 -> 2118489900000 | H67: =_xlfn.XLOOKUP($A67,$P$43:$P$57,$Q$43:$Q$57) -> 0.19701344 | I67: =_xlfn.XLOOKUP($A67,$P$43:$P$57,$R$43:$R$57) -> 0.11 | J67: =_xlfn.XLOOKUP($A67,$P$43:$P$57,$S$43:$S$57) -> 0.08
A68: {=INDEX($P$43:$P$57,INT((ROW()-43)/10)+1)} -> 2028 | B68: {=INDEX($L$43:$L$52,MOD(ROW()-43,10)+1)} -> D6 | C68: =_xlfn.XLOOKUP($B68,$L$43:$L$52,$M$43:$M$52)*10^9 -> 257300000000 | D68: =C68+D69 -> 1522300000000 | E68: =_xlfn.XLOOKUP($B68,$L$43:$L$52,$N$43:$N$52) -> 0.858 | F68: =C68*E68 -> 220763400000 | G68: =F68+G69 -> 1928166900000 | H68: =_xlfn.XLOOKUP($A68,$P$43:$P$57,$Q$43:$Q$57) -> 0.19701344 | I68: =_xlfn.XLOOKUP($A68,$P$43:$P$57,$R$43:$R$57) -> 0.11 | J68: =_xlfn.XLOOKUP($A68,$P$43:$P$57,$S$43:$S$57) -> 0.08
A69: {=INDEX($P$43:$P$57,INT((ROW()-43)/10)+1)} -> 2028 | B69: {=INDEX($L$43:$L$52,MOD(ROW()-43,10)+1)} -> D7 | C69: =_xlfn.XLOOKUP($B69,$L$43:$L$52,$M$43:$M$52)*10^9 -> 278500000000 | D69: =C69+D70 -> 1265000000000 | E69: =_xlfn.XLOOKUP($B69,$L$43:$L$52,$N$43:$N$52) -> 0.99 | F69: =C69*E69 -> 275715000000 | G69: =F69+G70 -> 1707403500000 | H69: =_xlfn.XLOOKUP($A69,$P$43:$P$57,$Q$43:$Q$57) -> 0.19701344 | I69: =_xlfn.XLOOKUP($A69,$P$43:$P$57,$R$43:$R$57) -> 0.11 | J69: =_xlfn.XLOOKUP($A69,$P$43:$P$57,$S$43:$S$57) -> 0.08
A70: {=INDEX($P$43:$P$57,INT((ROW()-43)/10)+1)} -> 2028 | B70: {=INDEX($L$43:$L$52,MOD(ROW()-43,10)+1)} -> D8 | C70: =_xlfn.XLOOKUP($B70,$L$43:$L$52,$M$43:$M$52)*10^9 -> 736500000000 | D70: =C70+D71 -> 986500000000 | E70: =_xlfn.XLOOKUP($B70,$L$43:$L$52,$N$43:$N$52) -> 1.249 | F70: =C70*E70 -> 9.198885e+11 | G70: =F70+G71 -> 1431688500000 | H70: =_xlfn.XLOOKUP($A70,$P$43:$P$57,$Q$43:$Q$57) -> 0.19701344 | I70: =_xlfn.XLOOKUP($A70,$P$43:$P$57,$R$43:$R$57) -> 0.11 | J70: =_xlfn.XLOOKUP($A70,$P$43:$P$57,$S$43:$S$57) -> 0.08
A71: {=INDEX($P$43:$P$57,INT((ROW()-43)/10)+1)} -> 2028 | B71: {=INDEX($L$43:$L$52,MOD(ROW()-43,10)+1)} -> D9 | C71: =_xlfn.XLOOKUP($B71,$L$43:$L$52,$M$43:$M$52)*10^9 -> 150000000000 | D71: =C71+D72 -> 250000000000 | E71: =_xlfn.XLOOKUP($B71,$L$43:$L$52,$N$43:$N$52) -> 1.58 | F71: =C71*E71 -> 237000000000 | G71: =F71+G72 -> 511800000000 | H71: =_xlfn.XLOOKUP($A71,$P$43:$P$57,$Q$43:$Q$57) -> 0.19701344 | I71: =_xlfn.XLOOKUP($A71,$P$43:$P$57,$R$43:$R$57) -> 0.11 | J71: =_xlfn.XLOOKUP($A71,$P$43:$P$57,$S$43:$S$57) -> 0.08
A72: {=INDEX($P$43:$P$57,INT((ROW()-43)/10)+1)} -> 2028 | B72: {=INDEX($L$43:$L$52,MOD(ROW()-43,10)+1)} -> D10 | C72: =_xlfn.XLOOKUP($B72,$L$43:$L$52,$M$43:$M$52)*10^9 -> 100000000000 | D72: =C72 -> 100000000000 | E72: =_xlfn.XLOOKUP($B72,$L$43:$L$52,$N$43:$N$52) -> 2.748 | F72: =C72*E72 -> 2.748e+11 | G72: =F72 -> 2.748e+11 | H72: =_xlfn.XLOOKUP($A72,$P$43:$P$57,$Q$43:$Q$57) -> 0.19701344 | I72: =_xlfn.XLOOKUP($A72,$P$43:$P$57,$R$43:$R$57) -> 0.11 | J72: =_xlfn.XLOOKUP($A72,$P$43:$P$57,$S$43:$S$57) -> 0.08
A73: {=INDEX($P$43:$P$57,INT((ROW()-43)/10)+1)} -> 2029 | B73: {=INDEX($L$43:$L$52,MOD(ROW()-43,10)+1)} -> D1 | C73: =_xlfn.XLOOKUP($B73,$L$43:$L$52,$M$43:$M$52)*10^9 -> 200000000000000 | D73: =C73+D74 -> 202371100000000 | E73: =_xlfn.XLOOKUP($B73,$L$43:$L$52,$N$43:$N$52) -> 0.443 | F73: =C73*E73 -> 88600000000000 | G73: =F73+G74 -> 91099582600000 | H73: =_xlfn.XLOOKUP($A73,$P$43:$P$57,$Q$43:$Q$57) -> 0.1903348 | I73: =_xlfn.XLOOKUP($A73,$P$43:$P$57,$R$43:$R$57) -> 0.07 | J73: =_xlfn.XLOOKUP($A73,$P$43:$P$57,$S$43:$S$57) -> 0.07
A74: {=INDEX($P$43:$P$57,INT((ROW()-43)/10)+1)} -> 2029 | B74: {=INDEX($L$43:$L$52,MOD(ROW()-43,10)+1)} -> D2 | C74: =_xlfn.XLOOKUP($B74,$L$43:$L$52,$M$43:$M$52)*10^9 -> 186000000000 | D74: =C74+D75 -> 2371100000000 | E74: =_xlfn.XLOOKUP($B74,$L$43:$L$52,$N$43:$N$52) -> 0.537 | F74: =C74*E74 -> 99882000000 | G74: =F74+G75 -> 2499582600000 | H74: =_xlfn.XLOOKUP($A74,$P$43:$P$57,$Q$43:$Q$57) -> 0.1903348 | I74: =_xlfn.XLOOKUP($A74,$P$43:$P$57,$R$43:$R$57) -> 0.07 | J74: =_xlfn.XLOOKUP($A74,$P$43:$P$57,$S$43:$S$57) -> 0.07
A75: {=INDEX($P$43:$P$57,INT((ROW()-43)/10)+1)} -> 2029 | B75: {=INDEX($L$43:$L$52,MOD(ROW()-43,10)+1)} -> D3 | C75: =_xlfn.XLOOKUP($B75,$L$43:$L$52,$M$43:$M$52)*10^9 -> 205000000000 | D75: =C75+D76 -> 2185100000000 | E75: =_xlfn.XLOOKUP($B75,$L$43:$L$52,$N$43:$N$52) -> 0.624 | F75: =C75*E75 -> 127920000000 | G75: =F75+G76 -> 2399700600000 | H75: =_xlfn.XLOOKUP($A75,$P$43:$P$57,$Q$43:$Q$57) -> 0.1903348 | I75: =_xlfn.XLOOKUP($A75,$P$43:$P$57,$R$43:$R$57) -> 0.07 | J75: =_xlfn.XLOOKUP($A75,$P$43:$P$57,$S$43:$S$57) -> 0.07
A76: {=INDEX($P$43:$P$57,INT((ROW()-43)/10)+1)} -> 2029 | B76: {=INDEX($L$43:$L$52,MOD(ROW()-43,10)+1)} -> D4 | C76: =_xlfn.XLOOKUP($B76,$L$43:$L$52,$M$43:$M$52)*10^9 -> 219300000000 | D76: =C76+D77 -> 1980100000000 | E76: =_xlfn.XLOOKUP($B76,$L$43:$L$52,$N$43:$N$52) -> 0.699 | F76: =C76*E76 -> 153290700000 | G76: =F76+G77 -> 2271780600000 | H76: =_xlfn.XLOOKUP($A76,$P$43:$P$57,$Q$43:$Q$57) -> 0.1903348 | I76: =_xlfn.XLOOKUP($A76,$P$43:$P$57,$R$43:$R$57) -> 0.07 | J76: =_xlfn.XLOOKUP($A76,$P$43:$P$57,$S$43:$S$57) -> 0.07
A77: {=INDEX($P$43:$P$57,INT((ROW()-43)/10)+1)} -> 2029 | B77: {=INDEX($L$43:$L$52,MOD(ROW()-43,10)+1)} -> D5 | C77: =_xlfn.XLOOKUP($B77,$L$43:$L$52,$M$43:$M$52)*10^9 -> 238500000000 | D77: =C77+D78 -> 1760800000000 | E77: =_xlfn.XLOOKUP($B77,$L$43:$L$52,$N$43:$N$52) -> 0.798 | F77: =C77*E77 -> 190323000000 | G77: =F77+G78 -> 2118489900000 | H77: =_xlfn.XLOOKUP($A77,$P$43:$P$57,$Q$43:$Q$57) -> 0.1903348 | I77: =_xlfn.XLOOKUP($A77,$P$43:$P$57,$R$43:$R$57) -> 0.07 | J77: =_xlfn.XLOOKUP($A77,$P$43:$P$57,$S$43:$S$57) -> 0.07
A78: {=INDEX($P$43:$P$57,INT((ROW()-43)/10)+1)} -> 2029 | B78: {=INDEX($L$43:$L$52,MOD(ROW()-43,10)+1)} -> D6 | C78: =_xlfn.XLOOKUP($B78,$L$43:$L$52,$M$43:$M$52)*10^9 -> 257300000000 | D78: =C78+D79 -> 1522300000000 | E78: =_xlfn.XLOOKUP($B78,$L$43:$L$52,$N$43:$N$52) -> 0.858 | F78: =C78*E78 -> 220763400000 | G78: =F78+G79 -> 1928166900000 | H78: =_xlfn.XLOOKUP($A78,$P$43:$P$57,$Q$43:$Q$57) -> 0.1903348 | I78: =_xlfn.XLOOKUP($A78,$P$43:$P$57,$R$43:$R$57) -> 0.07 | J78: =_xlfn.XLOOKUP($A78,$P$43:$P$57,$S$43:$S$57) -> 0.07
A79: {=INDEX($P$43:$P$57,INT((ROW()-43)/10)+1)} -> 2029 | B79: {=INDEX($L$43:$L$52,MOD(ROW()-43,10)+1)} -> D7 | C79: =_xlfn.XLOOKUP($B79,$L$43:$L$52,$M$43:$M$52)*10^9 -> 278500000000 | D79: =C79+D80 -> 1265000000000 | E79: =_xlfn.XLOOKUP($B79,$L$43:$L$52,$N$43:$N$52) -> 0.99 | F79: =C79*E79 -> 275715000000 | G79: =F79+G80 -> 1707403500000 | H79: =_xlfn.XLOOKUP($A79,$P$43:$P$57,$Q$43:$Q$57) -> 0.1903348 | I79: =_xlfn.XLOOKUP($A79,$P$43:$P$57,$R$43:$R$57) -> 0.07 | J79: =_xlfn.XLOOKUP($A79,$P$43:$P$57,$S$43:$S$57) -> 0.07
A80: {=INDEX($P$43:$P$57,INT((ROW()-43)/10)+1)} -> 2029 | B80: {=INDEX($L$43:$L$52,MOD(ROW()-43,10)+1)} -> D8 | C80: =_xlfn.XLOOKUP($B80,$L$43:$L$52,$M$43:$M$52)*10^9 -> 736500000000 | D80: =C80+D81 -> 986500000000 | E80: =_xlfn.XLOOKUP($B80,$L$43:$L$52,$N$43:$N$52) -> 1.249 | F80: =C80*E80 -> 9.198885e+11 | G80: =F80+G81 -> 1431688500000 | H80: =_xlfn.XLOOKUP($A80,$P$43:$P$57,$Q$43:$Q$57) -> 0.1903348 | I80: =_xlfn.XLOOKUP($A80,$P$43:$P$57,$R$43:$R$57) -> 0.07 | J80: =_xlfn.XLOOKUP($A80,$P$43:$P$57,$S$43:$S$57) -> 0.07
A81: {=INDEX($P$43:$P$57,INT((ROW()-43)/10)+1)} -> 2029 | B81: {=INDEX($L$43:$L$52,MOD(ROW()-43,10)+1)} -> D9 | C81: =_xlfn.XLOOKUP($B81,$L$43:$L$52,$M$43:$M$52)*10^9 -> 150000000000 | D81: =C81+D82 -> 250000000000 | E81: =_xlfn.XLOOKUP($B81,$L$43:$L$52,$N$43:$N$52) -> 1.58 | F81: =C81*E81 -> 237000000000 | G81: =F81+G82 -> 511800000000 | H81: =_xlfn.XLOOKUP($A81,$P$43:$P$57,$Q$43:$Q$57) -> 0.1903348 | I81: =_xlfn.XLOOKUP($A81,$P$43:$P$57,$R$43:$R$57) -> 0.07 | J81: =_xlfn.XLOOKUP($A81,$P$43:$P$57,$S$43:$S$57) -> 0.07
A82: {=INDEX($P$43:$P$57,INT((ROW()-43)/10)+1)} -> 2029 | B82: {=INDEX($L$43:$L$52,MOD(ROW()-43,10)+1)} -> D10 | C82: =_xlfn.XLOOKUP($B82,$L$43:$L$52,$M$43:$M$52)*10^9 -> 100000000000 | D82: =C82 -> 100000000000 | E82: =_xlfn.XLOOKUP($B82,$L$43:$L$52,$N$43:$N$52) -> 2.748 | F82: =C82*E82 -> 2.748e+11 | G82: =F82 -> 2.748e+11 | H82: =_xlfn.XLOOKUP($A82,$P$43:$P$57,$Q$43:$Q$57) -> 0.1903348 | I82: =_xlfn.XLOOKUP($A82,$P$43:$P$57,$R$43:$R$57) -> 0.07 | J82: =_xlfn.XLOOKUP($A82,$P$43:$P$57,$S$43:$S$57) -> 0.07
A83: {=INDEX($P$43:$P$57,INT((ROW()-43)/10)+1)} -> 2030 | B83: {=INDEX($L$43:$L$52,MOD(ROW()-43,10)+1)} -> D1 | C83: =_xlfn.XLOOKUP($B83,$L$43:$L$52,$M$43:$M$52)*10^9 -> 200000000000000 | D83: =C83+D84 -> 202371100000000 | E83: =_xlfn.XLOOKUP($B83,$L$43:$L$52,$N$43:$N$52) -> 0.443 | F83: =C83*E83 -> 88600000000000 | G83: =F83+G84 -> 91099582600000 | H83: =_xlfn.XLOOKUP($A83,$P$43:$P$57,$Q$43:$Q$57) -> 0.18544418 | I83: =_xlfn.XLOOKUP($A83,$P$43:$P$57,$R$43:$R$57) -> 0.06 | J83: =_xlfn.XLOOKUP($A83,$P$43:$P$57,$S$43:$S$57) -> 0.06
A84: {=INDEX($P$43:$P$57,INT((ROW()-43)/10)+1)} -> 2030 | B84: {=INDEX($L$43:$L$52,MOD(ROW()-43,10)+1)} -> D2 | C84: =_xlfn.XLOOKUP($B84,$L$43:$L$52,$M$43:$M$52)*10^9 -> 186000000000 | D84: =C84+D85 -> 2371100000000 | E84: =_xlfn.XLOOKUP($B84,$L$43:$L$52,$N$43:$N$52) -> 0.537 | F84: =C84*E84 -> 99882000000 | G84: =F84+G85 -> 2499582600000 | H84: =_xlfn.XLOOKUP($A84,$P$43:$P$57,$Q$43:$Q$57) -> 0.18544418 | I84: =_xlfn.XLOOKUP($A84,$P$43:$P$57,$R$43:$R$57) -> 0.06 | J84: =_xlfn.XLOOKUP($A84,$P$43:$P$57,$S$43:$S$57) -> 0.06
A85: {=INDEX($P$43:$P$57,INT((ROW()-43)/10)+1)} -> 2030 | B85: {=INDEX($L$43:$L$52,MOD(ROW()-43,10)+1)} -> D3 | C85: =_xlfn.XLOOKUP($B85,$L$43:$L$52,$M$43:$M$52)*10^9 -> 205000000000 | D85: =C85+D86 -> 2185100000000 | E85: =_xlfn.XLOOKUP($B85,$L$43:$L$52,$N$43:$N$52) -> 0.624 | F85: =C85*E85 -> 127920000000 | G85: =F85+G86 -> 2399700600000 | H85: =_xlfn.XLOOKUP($A85,$P$43:$P$57,$Q$43:$Q$57) -> 0.18544418 | I85: =_xlfn.XLOOKUP($A85,$P$43:$P$57,$R$43:$R$57) -> 0.06 | J85: =_xlfn.XLOOKUP($A85,$P$43:$P$57,$S$43:$S$57) -> 0.06
A86: {=INDEX($P$43:$P$57,INT((ROW()-43)/10)+1)} -> 2030 | B86: {=INDEX($L$43:$L$52,MOD(ROW()-43,10)+1)} -> D4 | C86: =_xlfn.XLOOKUP($B86,$L$43:$L$52,$M$43:$M$52)*10^9 -> 219300000000 | D86: =C86+D87 -> 1980100000000 | E86: =_xlfn.XLOOKUP($B86,$L$43:$L$52,$N$43:$N$52) -> 0.699 | F86: =C86*E86 -> 153290700000 | G86: =F86+G87 -> 2271780600000 | H86: =_xlfn.XLOOKUP($A86,$P$43:$P$57,$Q$43:$Q$57) -> 0.18544418 | I86: =_xlfn.XLOOKUP($A86,$P$43:$P$57,$R$43:$R$57) -> 0.06 | J86: =_xlfn.XLOOKUP($A86,$P$43:$P$57,$S$43:$S$57) -> 0.06
A87: {=INDEX($P$43:$P$57,INT((ROW()-43)/10)+1)} -> 2030 | B87: {=INDEX($L$43:$L$52,MOD(ROW()-43,10)+1)} -> D5 | C87: =_xlfn.XLOOKUP($B87,$L$43:$L$52,$M$43:$M$52)*10^9 -> 238500000000 | D87: =C87+D88 -> 1760800000000 | E87: =_xlfn.XLOOKUP($B87,$L$43:$L$52,$N$43:$N$52) -> 0.798 | F87: =C87*E87 -> 190323000000 | G87: =F87+G88 -> 2118489900000 | H87: =_xlfn.XLOOKUP($A87,$P$43:$P$57,$Q$43:$Q$57) -> 0.18544418 | I87: =_xlfn.XLOOKUP($A87,$P$43:$P$57,$R$43:$R$57) -> 0.06 | J87: =_xlfn.XLOOKUP($A87,$P$43:$P$57,$S$43:$S$57) -> 0.06
A88: {=INDEX($P$43:$P$57,INT((ROW()-43)/10)+1)} -> 2030 | B88: {=INDEX($L$43:$L$52,MOD(ROW()-43,10)+1)} -> D6 | C88: =_xlfn.XLOOKUP($B88,$L$43:$L$52,$M$43:$M$52)*10^9 -> 257300000000 | D88: =C88+D89 -> 1522300000000 | E88: =_xlfn.XLOOKUP($B88,$L$43:$L$52,$N$43:$N$52) -> 0.858 | F88: =C88*E88 -> 220763400000 | G88: =F88+G89 -> 1928166900000 | H88: =_xlfn.XLOOKUP($A88,$P$43:$P$57,$Q$43:$Q$57) -> 0.18544418 | I88: =_xlfn.XLOOKUP($A88,$P$43:$P$57,$R$43:$R$57) -> 0.06 | J88: =_xlfn.XLOOKUP($A88,$P$43:$P$57,$S$43:$S$57) -> 0.06
A89: {=INDEX($P$43:$P$57,INT((ROW()-43)/10)+1)} -> 2030 | B89: {=INDEX($L$43:$L$52,MOD(ROW()-43,10)+1)} -> D7 | C89: =_xlfn.XLOOKUP($B89,$L$43:$L$52,$M$43:$M$52)*10^9 -> 278500000000 | D89: =C89+D90 -> 1265000000000 | E89: =_xlfn.XLOOKUP($B89,$L$43:$L$52,$N$43:$N$52) -> 0.99 | F89: =C89*E89 -> 275715000000 | G89: =F89+G90 -> 1707403500000 | H89: =_xlfn.XLOOKUP($A89,$P$43:$P$57,$Q$43:$Q$57) -> 0.18544418 | I89: =_xlfn.XLOOKUP($A89,$P$43:$P$57,$R$43:$R$57) -> 0.06 | J89: =_xlfn.XLOOKUP($A89,$P$43:$P$57,$S$43:$S$57) -> 0.06
A90: {=INDEX($P$43:$P$57,INT((ROW()-43)/10)+1)} -> 2030 | B90: {=INDEX($L$43:$L$52,MOD(ROW()-43,10)+1)} -> D8 | C90: =_xlfn.XLOOKUP($B90,$L$43:$L$52,$M$43:$M$52)*10^9 -> 736500000000 | D90: =C90+D91 -> 986500000000 | E90: =_xlfn.XLOOKUP($B90,$L$43:$L$52,$N$43:$N$52) -> 1.249 | F90: =C90*E90 -> 9.198885e+11 | G90: =F90+G91 -> 1431688500000 | H90: =_xlfn.XLOOKUP($A90,$P$43:$P$57,$Q$43:$Q$57) -> 0.18544418 | I90: =_xlfn.XLOOKUP($A90,$P$43:$P$57,$R$43:$R$57) -> 0.06 | J90: =_xlfn.XLOOKUP($A90,$P$43:$P$57,$S$43:$S$57) -> 0.06
A91: {=INDEX($P$43:$P$57,INT((ROW()-43)/10)+1)} -> 2030 | B91: {=INDEX($L$43:$L$52,MOD(ROW()-43,10)+1)} -> D9 | C91: =_xlfn.XLOOKUP($B91,$L$43:$L$52,$M$43:$M$52)*10^9 -> 150000000000 | D91: =C91+D92 -> 250000000000 | E91: =_xlfn.XLOOKUP($B91,$L$43:$L$52,$N$43:$N$52) -> 1.58 | F91: =C91*E91 -> 237000000000 | G91: =F91+G92 -> 511800000000 | H91: =_xlfn.XLOOKUP($A91,$P$43:$P$57,$Q$43:$Q$57) -> 0.18544418 | I91: =_xlfn.XLOOKUP($A91,$P$43:$P$57,$R$43:$R$57) -> 0.06 | J91: =_xlfn.XLOOKUP($A91,$P$43:$P$57,$S$43:$S$57) -> 0.06
A92: {=INDEX($P$43:$P$57,INT((ROW()-43)/10)+1)} -> 2030 | B92: {=INDEX($L$43:$L$52,MOD(ROW()-43,10)+1)} -> D10 | C92: =_xlfn.XLOOKUP($B92,$L$43:$L$52,$M$43:$M$52)*10^9 -> 100000000000 | D92: =C92 -> 100000000000 | E92: =_xlfn.XLOOKUP($B92,$L$43:$L$52,$N$43:$N$52) -> 2.748 | F92: =C92*E92 -> 2.748e+11 | G92: =F92 -> 2.748e+11 | H92: =_xlfn.XLOOKUP($A92,$P$43:$P$57,$Q$43:$Q$57) -> 0.18544418 | I92: =_xlfn.XLOOKUP($A92,$P$43:$P$57,$R$43:$R$57) -> 0.06 | J92: =_xlfn.XLOOKUP($A92,$P$43:$P$57,$S$43:$S$57) -> 0.06
A93: {=INDEX($P$43:$P$57,INT((ROW()-43)/10)+1)} -> 2031 | B93: {=INDEX($L$43:$L$52,MOD(ROW()-43,10)+1)} -> D1 | C93: =_xlfn.XLOOKUP($B93,$L$43:$L$52,$M$43:$M$52)*10^9 -> 200000000000000 | D93: =C93+D94 -> 202371100000000 | E93: =_xlfn.XLOOKUP($B93,$L$43:$L$52,$N$43:$N$52) -> 0.443 | F93: =C93*E93 -> 88600000000000 | G93: =F93+G94 -> 91099582600000 | H93: =_xlfn.XLOOKUP($A93,$P$43:$P$57,$Q$43:$Q$57) -> 0.18176245 | I93: =_xlfn.XLOOKUP($A93,$P$43:$P$57,$R$43:$R$57) -> 0.04 | J93: =_xlfn.XLOOKUP($A93,$P$43:$P$57,$S$43:$S$57) -> 0.06
A94: {=INDEX($P$43:$P$57,INT((ROW()-43)/10)+1)} -> 2031 | B94: {=INDEX($L$43:$L$52,MOD(ROW()-43,10)+1)} -> D2 | C94: =_xlfn.XLOOKUP($B94,$L$43:$L$52,$M$43:$M$52)*10^9 -> 186000000000 | D94: =C94+D95 -> 2371100000000 | E94: =_xlfn.XLOOKUP($B94,$L$43:$L$52,$N$43:$N$52) -> 0.537 | F94: =C94*E94 -> 99882000000 | G94: =F94+G95 -> 2499582600000 | H94: =_xlfn.XLOOKUP($A94,$P$43:$P$57,$Q$43:$Q$57) -> 0.18176245 | I94: =_xlfn.XLOOKUP($A94,$P$43:$P$57,$R$43:$R$57) -> 0.04 | J94: =_xlfn.XLOOKUP($A94,$P$43:$P$57,$S$43:$S$57) -> 0.06
A95: {=INDEX($P$43:$P$57,INT((ROW()-43)/10)+1)} -> 2031 | B95: {=INDEX($L$43:$L$52,MOD(ROW()-43,10)+1)} -> D3 | C95: =_xlfn.XLOOKUP($B95,$L$43:$L$52,$M$43:$M$52)*10^9 -> 205000000000 | D95: =C95+D96 -> 2185100000000 | E95: =_xlfn.XLOOKUP($B95,$L$43:$L$52,$N$43:$N$52) -> 0.624 | F95: =C95*E95 -> 127920000000 | G95: =F95+G96 -> 2399700600000 | H95: =_xlfn.XLOOKUP($A95,$P$43:$P$57,$Q$43:$Q$57) -> 0.18176245 | I95: =_xlfn.XLOOKUP($A95,$P$43:$P$57,$R$43:$R$57) -> 0.04 | J95: =_xlfn.XLOOKUP($A95,$P$43:$P$57,$S$43:$S$57) -> 0.06
A96: {=INDEX($P$43:$P$57,INT((ROW()-43)/10)+1)} -> 2031 | B96: {=INDEX($L$43:$L$52,MOD(ROW()-43,10)+1)} -> D4 | C96: =_xlfn.XLOOKUP($B96,$L$43:$L$52,$M$43:$M$52)*10^9 -> 219300000000 | D96: =C96+D97 -> 1980100000000 | E96: =_xlfn.XLOOKUP($B96,$L$43:$L$52,$N$43:$N$52) -> 0.699 | F96: =C96*E96 -> 153290700000 | G96: =F96+G97 -> 2271780600000 | H96: =_xlfn.XLOOKUP($A96,$P$43:$P$57,$Q$43:$Q$57) -> 0.18176245 | I96: =_xlfn.XLOOKUP($A96,$P$43:$P$57,$R$43:$R$57) -> 0.04 | J96: =_xlfn.XLOOKUP($A96,$P$43:$P$57,$S$43:$S$57) -> 0.06
A97: {=INDEX($P$43:$P$57,INT((ROW()-43)/10)+1)} -> 2031 | B97: {=INDEX($L$43:$L$52,MOD(ROW()-43,10)+1)} -> D5 | C97: =_xlfn.XLOOKUP($B97,$L$43:$L$52,$M$43:$M$52)*10^9 -> 238500000000 | D97: =C97+D98 -> 1760800000000 | E97: =_xlfn.XLOOKUP($B97,$L$43:$L$52,$N$43:$N$52) -> 0.798 | F97: =C97*E97 -> 190323000000 | G97: =F97+G98 -> 2118489900000 | H97: =_xlfn.XLOOKUP($A97,$P$43:$P$57,$Q$43:$Q$57) -> 0.18176245 | I97: =_xlfn.XLOOKUP($A97,$P$43:$P$57,$R$43:$R$57) -> 0.04 | J97: =_xlfn.XLOOKUP($A97,$P$43:$P$57,$S$43:$S$57) -> 0.06
A98: {=INDEX($P$43:$P$57,INT((ROW()-43)/10)+1)} -> 2031 | B98: {=INDEX($L$43:$L$52,MOD(ROW()-43,10)+1)} -> D6 | C98: =_xlfn.XLOOKUP($B98,$L$43:$L$52,$M$43:$M$52)*10^9 -> 257300000000 | D98: =C98+D99 -> 1522300000000 | E98: =_xlfn.XLOOKUP($B98,$L$43:$L$52,$N$43:$N$52) -> 0.858 | F98: =C98*E98 -> 220763400000 | G98: =F98+G99 -> 1928166900000 | H98: =_xlfn.XLOOKUP($A98,$P$43:$P$57,$Q$43:$Q$57) -> 0.18176245 | I98: =_xlfn.XLOOKUP($A98,$P$43:$P$57,$R$43:$R$57) -> 0.04 | J98: =_xlfn.XLOOKUP($A98,$P$43:$P$57,$S$43:$S$57) -> 0.06
A99: {=INDEX($P$43:$P$57,INT((ROW()-43)/10)+1)} -> 2031 | B99: {=INDEX($L$43:$L$52,MOD(ROW()-43,10)+1)} -> D7 | C99: =_xlfn.XLOOKUP($B99,$L$43:$L$52,$M$43:$M$52)*10^9 -> 278500000000 | D99: =C99+D100 -> 1265000000000 | E99: =_xlfn.XLOOKUP($B99,$L$43:$L$52,$N$43:$N$52) -> 0.99 | F99: =C99*E99 -> 275715000000 | G99: =F99+G100 -> 1707403500000 | H99: =_xlfn.XLOOKUP($A99,$P$43:$P$57,$Q$43:$Q$57) -> 0.18176245 | I99: =_xlfn.XLOOKUP($A99,$P$43:$P$57,$R$43:$R$57) -> 0.04 | J99: =_xlfn.XLOOKUP($A99,$P$43:$P$57,$S$43:$S$57) -> 0.06
A100: {=INDEX($P$43:$P$57,INT((ROW()-43)/10)+1)} -> 2031 | B100: {=INDEX($L$43:$L$52,MOD(ROW()-43,10)+1)} -> D8 | C100: =_xlfn.XLOOKUP($B100,$L$43:$L$52,$M$43:$M$52)*10^9 -> 736500000000 | D100: =C100+D101 -> 986500000000 | E100: =_xlfn.XLOOKUP($B100,$L$43:$L$52,$N$43:$N$52) -> 1.249 | F100: =C100*E100 -> 9.198885e+11 | G100: =F100+G101 -> 1431688500000 | H100: =_xlfn.XLOOKUP($A100,$P$43:$P$57,$Q$43:$Q$57) -> 0.18176245 | I100: =_xlfn.XLOOKUP($A100,$P$43:$P$57,$R$43:$R$57) -> 0.04 | J100: =_xlfn.XLOOKUP($A100,$P$43:$P$57,$S$43:$S$57) -> 0.06
A101: {=INDEX($P$43:$P$57,INT((ROW()-43)/10)+1)} -> 2031 | B101: {=INDEX($L$43:$L$52,MOD(ROW()-43,10)+1)} -> D9 | C101: =_xlfn.XLOOKUP($B101,$L$43:$L$52,$M$43:$M$52)*10^9 -> 150000000000 | D101: =C101+D102 -> 250000000000 | E101: =_xlfn.XLOOKUP($B101,$L$43:$L$52,$N$43:$N$52) -> 1.58 | F101: =C101*E101 -> 237000000000 | G101: =F101+G102 -> 511800000000 | H101: =_xlfn.XLOOKUP($A101,$P$43:$P$57,$Q$43:$Q$57) -> 0.18176245 | I101: =_xlfn.XLOOKUP($A101,$P$43:$P$57,$R$43:$R$57) -> 0.04 | J101: =_xlfn.XLOOKUP($A101,$P$43:$P$57,$S$43:$S$57) -> 0.06
A102: {=INDEX($P$43:$P$57,INT((ROW()-43)/10)+1)} -> 2031 | B102: {=INDEX($L$43:$L$52,MOD(ROW()-43,10)+1)} -> D10 | C102: =_xlfn.XLOOKUP($B102,$L$43:$L$52,$M$43:$M$52)*10^9 -> 100000000000 | D102: =C102 -> 100000000000 | E102: =_xlfn.XLOOKUP($B102,$L$43:$L$52,$N$43:$N$52) -> 2.748 | F102: =C102*E102 -> 2.748e+11 | G102: =F102 -> 2.748e+11 | H102: =_xlfn.XLOOKUP($A102,$P$43:$P$57,$Q$43:$Q$57) -> 0.18176245 | I102: =_xlfn.XLOOKUP($A102,$P$43:$P$57,$R$43:$R$57) -> 0.04 | J102: =_xlfn.XLOOKUP($A102,$P$43:$P$57,$S$43:$S$57) -> 0.06
A103: {=INDEX($P$43:$P$57,INT((ROW()-43)/10)+1)} -> 2032 | B103: {=INDEX($L$43:$L$52,MOD(ROW()-43,10)+1)} -> D1 | C103: =_xlfn.XLOOKUP($B103,$L$43:$L$52,$M$43:$M$52)*10^9 -> 200000000000000 | D103: =C103+D104 -> 202371100000000 | E103: =_xlfn.XLOOKUP($B103,$L$43:$L$52,$N$43:$N$52) -> 0.443 | F103: =C103*E103 -> 88600000000000 | G103: =F103+G104 -> 91099582600000 | H103: =_xlfn.XLOOKUP($A103,$P$43:$P$57,$Q$43:$Q$57) -> 0.17893265 | I103: =_xlfn.XLOOKUP($A103,$P$43:$P$57,$R$43:$R$57) -> 0.04 | J103: =_xlfn.XLOOKUP($A103,$P$43:$P$57,$S$43:$S$57) -> 0.06
A104: {=INDEX($P$43:$P$57,INT((ROW()-43)/10)+1)} -> 2032 | B104: {=INDEX($L$43:$L$52,MOD(ROW()-43,10)+1)} -> D2 | C104: =_xlfn.XLOOKUP($B104,$L$43:$L$52,$M$43:$M$52)*10^9 -> 186000000000 | D104: =C104+D105 -> 2371100000000 | E104: =_xlfn.XLOOKUP($B104,$L$43:$L$52,$N$43:$N$52) -> 0.537 | F104: =C104*E104 -> 99882000000 | G104: =F104+G105 -> 2499582600000 | H104: =_xlfn.XLOOKUP($A104,$P$43:$P$57,$Q$43:$Q$57) -> 0.17893265 | I104: =_xlfn.XLOOKUP($A104,$P$43:$P$57,$R$43:$R$57) -> 0.04 | J104: =_xlfn.XLOOKUP($A104,$P$43:$P$57,$S$43:$S$57) -> 0.06
A105: {=INDEX($P$43:$P$57,INT((ROW()-43)/10)+1)} -> 2032 | B105: {=INDEX($L$43:$L$52,MOD(ROW()-43,10)+1)} -> D3 | C105: =_xlfn.XLOOKUP($B105,$L$43:$L$52,$M$43:$M$52)*10^9 -> 205000000000 | D105: =C105+D106 -> 2185100000000 | E105: =_xlfn.XLOOKUP($B105,$L$43:$L$52,$N$43:$N$52) -> 0.624 | F105: =C105*E105 -> 127920000000 | G105: =F105+G106 -> 2399700600000 | H105: =_xlfn.XLOOKUP($A105,$P$43:$P$57,$Q$43:$Q$57) -> 0.17893265 | I105: =_xlfn.XLOOKUP($A105,$P$43:$P$57,$R$43:$R$57) -> 0.04 | J105: =_xlfn.XLOOKUP($A105,$P$43:$P$57,$S$43:$S$57) -> 0.06
A106: {=INDEX($P$43:$P$57,INT((ROW()-43)/10)+1)} -> 2032 | B106: {=INDEX($L$43:$L$52,MOD(ROW()-43,10)+1)} -> D4 | C106: =_xlfn.XLOOKUP($B106,$L$43:$L$52,$M$43:$M$52)*10^9 -> 219300000000 | D106: =C106+D107 -> 1980100000000 | E106: =_xlfn.XLOOKUP($B106,$L$43:$L$52,$N$43:$N$52) -> 0.699 | F106: =C106*E106 -> 153290700000 | G106: =F106+G107 -> 2271780600000 | H106: =_xlfn.XLOOKUP($A106,$P$43:$P$57,$Q$43:$Q$57) -> 0.17893265 | I106: =_xlfn.XLOOKUP($A106,$P$43:$P$57,$R$43:$R$57) -> 0.04 | J106: =_xlfn.XLOOKUP($A106,$P$43:$P$57,$S$43:$S$57) -> 0.06
A107: {=INDEX($P$43:$P$57,INT((ROW()-43)/10)+1)} -> 2032 | B107: {=INDEX($L$43:$L$52,MOD(ROW()-43,10)+1)} -> D5 | C107: =_xlfn.XLOOKUP($B107,$L$43:$L$52,$M$43:$M$52)*10^9 -> 238500000000 | D107: =C107+D108 -> 1760800000000 | E107: =_xlfn.XLOOKUP($B107,$L$43:$L$52,$N$43:$N$52) -> 0.798 | F107: =C107*E107 -> 190323000000 | G107: =F107+G108 -> 2118489900000 | H107: =_xlfn.XLOOKUP($A107,$P$43:$P$57,$Q$43:$Q$57) -> 0.17893265 | I107: =_xlfn.XLOOKUP($A107,$P$43:$P$57,$R$43:$R$57) -> 0.04 | J107: =_xlfn.XLOOKUP($A107,$P$43:$P$57,$S$43:$S$57) -> 0.06
...

Sheet Monte Carlo Single Simulation
A1: Monte Carlo Single Simulation
A2: Blue text indicates assumptions that can be altered; altering one input may require altering another input in order to get reasonable results.
A3: Black text indicates cells with formulas or cells with static values that are not meant to be altered.
A4: Note: To utilize the Monte Carlo, you need to use the "Calculate Now" button in excel, not "Calculate Sheet".
A5: Values are in millions unless otherwise specified except for per share amounts, multiples, and ratios. | H5: Results Box
H6: 2031 Suggested Share Price | N6: =N180 -> 3923.8198
H7: CAGR | N7: =N182 -> 0.58603625
B8: 2019 | C8: =B8+1 -> 2020 | D8: =C8+1 -> 2021 | E8: =D8+1 -> 2022 | F8: =E8+1 -> 2023 | G8: =F8+1 -> 2024 | H8: =G8+1 -> 2025 | I8: =H8+1 -> 2026 | J8: =I8+1 -> 2027 | ... N8: =M8+1 -> 2031 | AA8: Notes
A9: Key Drivers
A10: Max annual vehicle production increase (given management bandwidth constraints) | N10: ='Tesla Valuation Inputs'!G10 -> 0.40507328 | AA10: Provides an upper bound for vehicle production to accommodate management bandwidth constraints in building out factories.
A11: Miles traveled per robotaxi (not in millions) | N11: ='Tesla Valuation Inputs'!G11 -> 74200.303 | AA11: Elon Musk has previously stated that a robotaxi could have ~5-6x greater utilization than human-driven vehicle (~11,000 miles per year).
A12: Takeover time for autonomous adoption (years between 10% and 90% market saturation) | N12: ='Tesla Valuation Inputs'!G12 -> 5.2343191 | AA12: Time from 10% to 90% saturation
A13: Max annual Optimi production increase (given management bandwidth constraints) | N13: ='Tesla Valuation Inputs'!G13 -> 2.6548271 | AA13: Provides an upper bound for Optimus production to accommodate management bandwidth constraints in building out factories.
A14: Balance sheet assumptions
A15: Percent of factory-build/internal fleet that will be debt funded | N15: ='Tesla Valuation Inputs'!G15 -> 0.15850238 | AA15: Determines how much debt Tesla raises as it scales
A16: Vehicle capital efficiency 2031 (gross capex per vehicle produced, not in millions) | N16: ='Tesla Valuation Inputs'!G16 -> 6348.8086 | O16: Floor: | P16: 1800 | Q16: Ceiling: | R16: 15400 | AA16: The cost per vehicle of new production capacity. Lower = more efficient
A17: % of Year-end cash that's dedicated to AI Infrastructure and Chip Development | N17: ='Tesla Valuation Inputs'!G17 -> 0.14541062 | AA17: % of Year-end cash that goes towards AI infrastructure and Chip Development
A18: Bitcoin price appreciation (depreciation) annual | N18: ='Tesla Valuation Inputs'!G18 -> -0.12771641 | AA18: Bitcoin price appreciation (depreciation) annual. For more information on ARK's bitcoin research, see https://www.ark-invest.com/big-ideas-2026
A19: Weighted average market capitalization at which equity is raised (millions) | N19: ='Tesla Valuation Inputs'!G19 -> 1846881.4 | AA19: For simplicity, assume all Tesla equity raise occurs at this valuation. Note as modeled, this is not used, however users can change the Monte Carlo inputs to activate this line.
A20: Equity raise for capex (millions) | N20: ='Tesla Valuation Inputs'!G20 -> 0 | AA20: Assumption on Tesla Equity raise over the next five years. Note as modeled, this is not used, however users can change the Monte Carlo inputs to activate this line.
A21: Margin Assumptions
A22: Max gross margin on vehicle sales | N22: ='Tesla Valuation Inputs'!G22 -> 0.28066579 | AA22: Gross margin is driven by Wright's Law. This input is the max gross margin that the model allows Tesla to achieve. For more on Wright's Law, see: https://ark-invest.com/wrights-law/
A23: Wright's Law learning rate | N23: ='Tesla Valuation Inputs'!G23 -> 0.16553012 | AA23: The percent cost decline for every cumulative doubling of production.
A24: Electric Vehicle factory utilization factor | N24: ='Tesla Valuation Inputs'!G24 -> 0.7 | AA24: This is based on Tesla's historical utilization rates. Applied uniformly across all years.
A25: Percent of each model/price segment that Tesla penetrates | N25: ='Tesla Valuation Inputs'!G25 -> 0.068013237 | AA25: See ASP Tables tab. Provides an upper bound for addressable market within each vehicle segment.
A26: Tax rate | N26: ='Tesla Valuation Inputs'!G26 -> 0.21258129 | AA26: Tax rate applied to profits.
A27: Interest rate | N27: ='Tesla Valuation Inputs'!G27 -> 0.034487119 | AA27: Applied uniformly across all years for simplicity
A28: EBITDA As A % of Gross Margin - Electric Vehicle | N28: ='Tesla Valuation Inputs'!G28 -> 0.77597188 | AA28: EBITDA as a % of Gross Margin for the EV business.
A29: EBITDA As A % of Gross Margin - Stationary Energy Storage | N29: ='Tesla Valuation Inputs'!G29 -> 0.70984475 | AA29: EBITDA as a % of Gross Margin for the Stationary Energy Storage business.
A30: EBITDA As A % of Gross Margin - Optimus Hardware Sales | N30: ='Tesla Valuation Inputs'!G30 -> 0.8 | AA30: EBITDA as a % of Gross Margin for external Optimus hardware sales.
A31: EBITDA As A % of Gross Margin - Optimus RaaS | N31: ='Tesla Valuation Inputs'!G31 -> 0.79953231 | AA31: EBITDA as a % of Gross Margin for the Optimus Robot-as-a-Service (software subscription) business.
A32: Autonomous Assumptions
A33: Percent of customer owned fleet in China | N33: ='Tesla Valuation Inputs'!G33 -> 0.37694604 | AA33: What % of Tesla's Fleet is in China
A34: Maximum robotaxis Tesla will own & operate itself (not in millions) | N34: ='Tesla Valuation Inputs'!G34 -> 3443.1085 | AA34: This is a cap applied to the maximum number of robotaxis that Tesla will own and operate before partnering.
A35: Stationary Energy Storage Assumptions
A36: Stationary energy storage capital efficiency 2031 (gross capex per MWh deployed, not in millions) | N36: ='Tesla Valuation Inputs'!G36 -> 7981.6733 | O36: Floor: | P36: 4500 | Q36: Ceiling: | R36: 11000 | AA36: The cost per MWh deployed of new production capacity. Lower = more efficient
A37: Max annual energy increase (given management bandwidth constraints) | N37: ='Tesla Valuation Inputs'!G37 -> 0.98115305 | AA37: Provides an upper bound for energy production to accommodate management bandwidth constraints in building out factories.
A38: Gross margin of stationary energy storage business in 2031 | N38: ='Tesla Valuation Inputs'!G38 -> 0.24214251 | O38: Floor: | P38: 0.09 | Q38: Ceiling: | R38: 0.44 | AA38: This is the gross margin that will be applied to the stationary energy business in 2031. CAGR to this value from 2025.
A39: Optimus Assumptions
A40: Optimus Capability Increase For Every Cumulative Doubling in AI Spend | N40: ='Tesla Valuation Inputs'!G40 -> 0.10423006 | AA40: For every cumulative doubling in compute spend, Optimus performance will increase by this percent.
A41: What year does Tesla begin selling Optimi externally? | N41: ='Tesla Valuation Inputs'!G41 -> 2029 | AA41: Year Tesla begins selling Optimus units externally. Before this year, 100% of Optimi produced are deployed internally in Tesla factories; after, allocation splits between internal use (subject to the in-house cap below) and external sale.
A42: Once available for external use - what % of Optimi production does Tesla dedicate to in-house use up until the cap is reached? | N42: ='Tesla Valuation Inputs'!G42 -> 0.03430329 | AA42: Once external sales begin, the % of annual Optimus production Tesla still dedicates to in-house factory use, until the maximum internal fleet cap is reached.
A43: Maximum Optimi deployed in the factory | N43: ='Tesla Valuation Inputs'!G43 -> 75885.943 | AA43: Hard cap on the cumulative number of Optimi Tesla deploys in its own factories. The cap governs the internal/external allocation from the external-sales year (row 42) onward; before external sales begin, all production is deployed internally. Once the cap is reached, all incremental production is sold externally. For context, in 2025, Tesla's total global headcount was ~135k.
A44: Optimi capital efficiency 2031 (gross capex per Optimi produced, not in millions) | N44: ='Tesla Valuation Inputs'!G44 -> 6708.2128 | O44: Floor: | P44: 450 | Q44: Ceiling: | R44: 22000 | AA44: The cost per Optimus unit of new production capacity (gross capex per unit). Lower = more efficient.
A45: Optimi Hardware Gross Margin | N45: ='Tesla Valuation Inputs'!G45 -> 0.34876011 | AA45: Assumed Gross Margin for Optimus Hardware Sales
A46: RaaS Gross Margin (software subscription margin) | N46: ='Tesla Valuation Inputs'!G46 -> 0.76046081 | AA46: Gross margin on Optimus software subscription (RaaS) revenue. Software-like margin structure - high incremental gross margin once the product is built.
A47: Balance Sheet | B47: 2019 | C47: =B47+1 -> 2020 | D47: =C47+1 -> 2021 | E47: =D47+1 -> 2022 | F47: =E47+1 -> 2023 | G47: =F47+1 -> 2024 | H47: =G47+1 -> 2025 | I47: =H47+1 -> 2026 | J47: =I47+1 -> 2027 | ... W47: =V47+1 -> 2040
A48: Cash Logic
A49: Year End Cash For Investment | B49: =6268*10^6 -> 6268000000 | C49: =19384*10^6 -> 19384000000 | D49: =17576*10^6 -> 17576000000 | E49: =22185*10^6 -> 22185000000 | F49: =29094*10^6 -> 29094000000 | G49: =36563*10^6 -> 36563000000 | H49: =44059*10^6 -> 44059000000 | I49: =I163+H56 -> 4.9963657e+10 | J49: =J163+I56 -> 6.9387341e+10 | K49: =K163+J56 -> 1.1991685e+11 | L49: =L163+K56 -> 2.5642635e+11 | M49: =M163+L56 -> 5.3740435e+11 | N49: =N163+M56 -> 1.0608719e+12 | O49: =O163+N56 -> 2.027978e+12 | P49: =P163+O56 -> 4.0872679e+12 | ... W49: =W163+V56 -> 3.718982e+16 | AA49: [Cash generated]+[cash not deployed in the previous year due to scaling constraint]
A50: AI Infrastructure & Chip Development Capex T+1 | B50: 0 | C50: 0 | D50: 0 | E50: 0 | F50: 0 | G50: 0 | H50: =H49*$N$17 -> 6.4066466e+09 | I50: =I49*$N$17 -> 7.2652465e+09 | J50: =J49*$N$17 -> 1.0089656e+10 | K50: =K49*$N$17 -> 1.7437184e+10 | L50: =L49*$N$17 -> 3.7287114e+10 | M50: =M49*$N$17 -> 7.81443e+10 | N50: =N49*$N$17 -> 1.5426204e+11 | O50: =O49*$N$17 -> 4.5926401e+11 | ... W50: =W49*$N$17 -> 8.4221554e+15 | AA50: AI Infrastructure & Chip Development capex for next year = [Year end cash] * [% dedicated to AI Infrastructure input]. Carved out before the cash-allocation algorithm runs across vehicles/storage/Optimus.
A51: Cash Required for Capitalized Optimi/Robotaxi Fleet T+1 | H51: =IF(((I71-H71)+(I72-H72))*(1-$N$15)<0,0,((I71-H71)+(I72-H72))*(1-$N$15)) -> 1.840224e+08 | I51: =IF(((J71-I71)+(J72-I72))*(1-$N$15)<0,0,((J71-I71)+(J72-I72))*(1-$N$15)) -> 2.0585025e+08 | J51: =IF(((K71-J71)+(K72-J72))*(1-$N$15)<0,0,((K71-J71)+(K72-J72))*(1-$N$15)) -> 5.2843996e+08 | K51: =IF(((L71-K71)+(L72-K72))*(1-$N$15)<0,0,((L71-K71)+(L72-K72))*(1-$N$15)) -> 47048131 | L51: =IF(((M71-L71)+(M72-L72))*(1-$N$15)<0,0,((M71-L71)+(M72-L72))*(1-$N$15)) -> 1.2246145e+08 | M51: =IF(((N71-M71)+(N72-M72))*(1-$N$15)<0,0,((N71-M71)+(N72-M72))*(1-$N$15)) -> 3.1900187e+08 | N51: =IF(((O71-N71)+(O72-N72))*(1-$N$15)<0,0,((O71-N71)+(O72-N72))*(1-$N$15)) -> 2.8167157e+08 | O51: =IF(((P71-O71)+(P72-O72))*(1-$N$15)<0,0,((P71-O71)+(P72-O72))*(1-$N$15)) -> 0 | ... W51: =IF(((X71-W71)+(X72-W72))*(1-$N$15)<0,0,((X71-W71)+(X72-W72))*(1-$N$15)) -> 0 | AA51: Cash required for capitalized Optimi/Robotaxi Fleet T+1 = MAX(0, ([next-year gross cost of cumulative Optimi deployed internally] - [current-year gross cost]) + ([next-year gross cost of Robotaxi fleet] - [current-year gross cost])) * (1 - [% factory debt-funded]). Reserves the cash-funded portion of internally capitalized fleet assets before calculating cash available for PP&E; the debt-funded portion is captured through total PP&E growth and the debt funding line.
A52: Cash Raised for Capex Investment | J52: =$N$20/5 -> 0 | K52: =$N$20/5 -> 0 | L52: =$N$20/5 -> 0 | M52: =$N$20/5 -> 0 | N52: =$N$20/5 -> 0 | O52: 0 | P52: 0 | Q52: 0 | R52: 0 | S52: 0 | T52: 0 | U52: 0 | V52: 0 | W52: 0 | AA52: Cash received from capex equity raise. For simplicity, assume the cash is evenly spread out over the 5 years to 2031.
A53: Cash Available For PPE Investment T+1 | B53: =B49-B50-B51+B52 -> 6268000000 | C53: =C49-C50-C51+C52 -> 19384000000 | D53: =D49-D50-D51+D52 -> 17576000000 | E53: =E49-E50-E51+E52 -> 22185000000 | F53: =F49-F50-F51+F52 -> 29094000000 | G53: =G49-G50-G51+G52 -> 36563000000 | H53: =H49-H50-H51+H52 -> 3.7468331e+10 | I53: =I49-I50-I51+I52 -> 4.2492561e+10 | ... W53: =W49-W50-W51+W52 -> 2.8767665e+16 | AA53: [Year end cash for investment] - [AI Infrastructure & Chip Development capex T+1] - [Cash required for capitalized Optimi/Robotaxi Fleet T+1] + [Cash Raised]. The cash actually available to deploy across vehicle, storage, Optimus.
A54: Max Cash Deployable Given Scaling Constraint T+1 | B54: =(C85*$N10)*D88*(1-$N15)+(C121*$N37)*D128*(1-$N15)+(C130*$N13)*D132*(1-$N15) -> 1.3553647e+09 | C54: =(D85*$N10)*E88*(1-$N15)+(D121*$N37)*E128*(1-$N15)+(D130*$N13)*E132*(1-$N15) -> 4.7169104e+09 | D54: =(E85*$N10)*F88*(1-$N15)+(E121*$N37)*F128*(1-$N15)+(E130*$N13)*F132*(1-$N15) -> 7.040656e+09 | E54: =(F85*$N10)*G88*(1-$N15)+(F121*$N37)*G128*(1-$N15)+(F130*$N13)*G132*(1-$N15) -> 9.5236605e+09 | F54: =(G85*$N10)*H88*(1-$N15)+(G121*$N37)*H128*(1-$N15)+(G130*$N13)*H132*(1-$N15) -> 9.24913e+09 | G54: =(H85*$N10)*I88*(1-$N15)+(H121*$N37)*I128*(1-$N15)+(H130*$N13)*I132*(1-$N15) -> 7.6067339e+09 | H54: =(I85*$N10)*J88*(1-$N15)+(I121*$N37)*J128*(1-$N15)+(I130*$N13)*J132*(1-$N15) -> 9.5268184e+09 | I54: =(J85*$N10)*K88*(1-$N15)+(J121*$N37)*K128*(1-$N15)+(J130*$N13)*K132*(1-$N15) -> 1.211823e+10 | ... W54: =(X85*$N10)*Y88*(1-$N15)+(X121*$N37)*Y128*(1-$N15)+(X130*$N13)*Y132*(1-$N15) -> 0 | AA54: [Maximum increase in cars produceable allowable]*[Capex per unit production] + [Maximum increase in storage deployable]*[Storage capex per MWh] + [Maximum increase in Optimi produceable]*[Optimus capex per unit]. All adjusted for (1-[% factory debt-funded]). Represents the total capital Tesla could deploy if scaling all business lines at their maximum rates simultaneously.
A55: Bitcoin Value | E55: =9720*30397.55 -> 295464186 | F55: =9720*66500 -> 646380000 | G55: =1076*10^6 -> 1076000000 | H55: =1008*10^6 -> 1008000000 | I55: =H55*(1+$N$18) -> 8.7926185e+08 | J55: =I55*(1+$N$18) -> 7.6696568e+08 | K55: =J55*(1+$N$18) -> 6.6901158e+08 | L55: =K55*(1+$N$18) -> 5.8356782e+08 | M55: =L55*(1+$N$18) -> 5.0903663e+08 | N55: =M55*(1+$N$18) -> 4.4402429e+08 | O55: =N55*(1+$N$18) -> 3.873151e+08 | P55: =O55*(1+$N$18) -> 3.3784861e+08 | ... W55: =V55*(1+$N$18) -> 1.2981535e+08 | AA55: Year-end bitcoin value.
A56: Spillover Cash Not Deployed | B56: =IF(B53-B54>0,B53-B54,0) -> 4.9126353e+09 | C56: =IF(C53-C54>0,C53-C54,0) -> 1.466709e+10 | D56: =IF(D53-D54>0,D53-D54,0) -> 1.0535344e+10 | E56: =IF(E53-E54>0,E53-E54,0) -> 1.2661339e+10 | F56: =IF(F53-F54>0,F53-F54,0) -> 1.984487e+10 | G56: =IF(G53-G54>0,G53-G54,0) -> 2.8956266e+10 | H56: =IF(H53-H54>0,H53-H54,0) -> 2.7941513e+10 | I56: =IF(I53-I54>0,I53-I54,0) -> 3.0374331e+10 | ... W56: =IF(W53-W54>0,W53-W54,0) -> 2.8767665e+16 | AA56: Residual cash carried forward = max([Cash available after AI/fleet reserve] - [Maximum cash deployable given scaling constraints], 0). Negative residuals are floored at zero; cash shortfalls reduce available investment through the cash availability rows rather than being stored here.
A57: Capital Allocation
A58: Marginal 5Y IRR - Vehicles | H58: =IFERROR(IRR(CHOOSE({1;2;3;4;5;6}, -G88, (G90*G96)+G103*G113, G103*G113, G103*G113, G103*G113, G103*G113)),0) -> -0.66941152 | I58: =IFERROR(IRR(CHOOSE({1;2;3;4;5;6}, -H88, (H90*H96)+H103*H113, H103*H113, H103*H113, H103*H113, H103*H113)),0) -> -0.67218247 | J58: =IFERROR(IRR(CHOOSE({1;2;3;4;5;6}, -I88, (I90*I96)+I103*I113, I103*I113, I103*I113, I103*I113, I103*I113)),0) -> 12.753295 | K58: =IFERROR(IRR(CHOOSE({1;2;3;4;5;6}, -J88, (J90*J96)+J103*J113, J103*J113, J103*J113, J103*J113, J103*J113)),0) -> 15.974001 | L58: =IFERROR(IRR(CHOOSE({1;2;3;4;5;6}, -K88, (K90*K96)+K103*K113, K103*K113, K103*K113, K103*K113, K103*K113)),0) -> 18.966523 | M58: =IFERROR(IRR(CHOOSE({1;2;3;4;5;6}, -L88, (L90*L96)+L103*L113, L103*L113, L103*L113, L103*L113, L103*L113)),0) -> 22.218462 | N58: =IFERROR(IRR(CHOOSE({1;2;3;4;5;6}, -M88, (M90*M96)+M103*M113, M103*M113, M103*M113, M103*M113, M103*M113)),0) -> 20.053867 | O58: =IFERROR(IRR(CHOOSE({1;2;3;4;5;6}, -N88, (N90*N96)+N103*N113, N103*N113, N103*N113, N103*N113, N103*N113)),0) -> 16.79841 | ... W58: =IFERROR(IRR(CHOOSE({1;2;3;4;5;6}, -V88, (V90*V96)+V103*V113, V103*V113, V103*V113, V103*V113, V103*V113)),0) -> 7.2646068 | AA58: 5-year IRR on the next marginal dollar of vehicle capex. Outflow = [Vehicle capex per unit]; Year 1 inflow = [Vehicle hardware EBITDA] + [Robotaxi software EBITDA], Years 2-5 = [Robotaxi software EBITDA] recurring. Used to rank vehicles vs. storage vs. Optimus when allocating cash-constrained capex.
A59: Marginal 5Y IRR - Storage | H59: =IFERROR(IRR(CHOOSE({1;2;3;4;5;6}, -G128, G122*1000*G127, 0, 0, 0, 0)),0) -> 7.5258878 | I59: =IFERROR(IRR(CHOOSE({1;2;3;4;5;6}, -H128, H122*1000*H127, 0, 0, 0, 0)),0) -> 7.2558267 | J59: =IFERROR(IRR(CHOOSE({1;2;3;4;5;6}, -I128, I122*1000*I127, 0, 0, 0, 0)),0) -> 5.2430748 | K59: =IFERROR(IRR(CHOOSE({1;2;3;4;5;6}, -J128, J122*1000*J127, 0, 0, 0, 0)),0) -> 3.7210273 | L59: =IFERROR(IRR(CHOOSE({1;2;3;4;5;6}, -K128, K122*1000*K127, 0, 0, 0, 0)),0) -> 2.5700516 | M59: =IFERROR(IRR(CHOOSE({1;2;3;4;5;6}, -L128, L122*1000*L127, 0, 0, 0, 0)),0) -> 1.6996811 | N59: =IFERROR(IRR(CHOOSE({1;2;3;4;5;6}, -M128, M122*1000*M127, 0, 0, 0, 0)),0) -> 1.0415049 | O59: =IFERROR(IRR(CHOOSE({1;2;3;4;5;6}, -N128, N122*1000*N127, 0, 0, 0, 0)),0) -> 0.54379065 | ... W59: =IFERROR(IRR(CHOOSE({1;2;3;4;5;6}, -V128, V122*1000*V127, 0, 0, 0, 0)),0) -> -0.63869389 | AA59: 5-year IRR on the next marginal dollar of storage capex. Outflow = [Storage capex per MWh]; Year 1 inflow = [Storage EBITDA per MWh]. Used to rank business lines for cash-constrained capex allocation.
A60: Marginal 5Y IRR - Optimus | H60: =IFERROR(IRR(CHOOSE({1;2;3;4;5;6}, -G132, (G143*G147)+G150*G155, G150*G155, G150*G155, G150*G155, G150*G155)),0) -> 0 | I60: =IFERROR(IRR(CHOOSE({1;2;3;4;5;6}, -H132, (H143*H147)+H150*H155, H150*H155, H150*H155, H150*H155, H150*H155)),0) -> 0 | J60: =IFERROR(IRR(CHOOSE({1;2;3;4;5;6}, -I132, (I143*I147)+I150*I155, I150*I155, I150*I155, I150*I155, I150*I155)),0) -> 0 | K60: =IFERROR(IRR(CHOOSE({1;2;3;4;5;6}, -J132, (J143*J147)+J150*J155, J150*J155, J150*J155, J150*J155, J150*J155)),0) -> 0 | L60: =IFERROR(IRR(CHOOSE({1;2;3;4;5;6}, -K132, (K143*K147)+K150*K155, K150*K155, K150*K155, K150*K155, K150*K155)),0) -> 0 | M60: =IFERROR(IRR(CHOOSE({1;2;3;4;5;6}, -L132, (L143*L147)+L150*L155, L150*L155, L150*L155, L150*L155, L150*L155)),0) -> 8.9453277 | N60: =IFERROR(IRR(CHOOSE({1;2;3;4;5;6}, -M132, (M143*M147)+M150*M155, M150*M155, M150*M155, M150*M155, M150*M155)),0) -> 12.128436 | O60: =IFERROR(IRR(CHOOSE({1;2;3;4;5;6}, -N132, (N143*N147)+N150*N155, N150*N155, N150*N155, N150*N155, N150*N155)),0) -> 16.812613 | ... W60: =IFERROR(IRR(CHOOSE({1;2;3;4;5;6}, -V132, (V143*V147)+V150*V155, V150*V155, V150*V155, V150*V155, V150*V155)),0) -> 362.21672 | AA60: 5-year IRR on the next marginal dollar of Optimus capex. Outflow = [Optimus capex per unit]; Year 1 inflow = [Optimus hardware EBITDA] + [Optimus software EBITDA], Years 2-5 = [Optimus software EBITDA] recurring. Used to rank business lines for cash-constrained capex allocation.
A61: Max Capex Deployable - Vehicles | H61: =(H85*$N$10)*I88 -> 8.7116875e+09 | I61: =(I85*$N$10)*J88 -> 1.0606402e+10 | J61: =(J85*$N$10)*K88 -> 1.29132e+10 | K61: =(K85*$N$10)*L88 -> 1.5721707e+10 | L61: =(L85*$N$10)*M88 -> 1.9141039e+10 | M61: =(M85*$N$10)*N88 -> 2.3304045e+10 | N61: =(N85*$N$10)*O88 -> 2.8372467e+10 | O61: =(O85*$N$10)*P88 -> 3.4543227e+10 | ... W61: =(W85*$N$10)*X88 -> 0 | AA61: Maximum vehicle capex that could be deployed this year given scaling constraints. [Current year vehicle units] * [Max annual scaling rate for vehicles] * [Vehicle capex per unit next year]. Represents the upper bound before cash availability is considered.
A62: Max Capex Deployable - Storage | H62: =(H121*$N$37)*I128 -> 3.2783174e+08 | I62: =(I121*$N$37)*J128 -> 6.6384753e+08 | J62: =(J121*$N$37)*K128 -> 1.3442675e+09 | K62: =(K121*$N$37)*L128 -> 2.7220935e+09 | L62: =(L121*$N$37)*M128 -> 5.5121418e+09 | M62: =(M121*$N$37)*N128 -> 1.116189e+10 | N62: =(N121*$N$37)*O128 -> 2.2602427e+10 | O62: =(O121*$N$37)*P128 -> 4.5769105e+10 | ... W62: =(W121*$N$37)*X128 -> 0 | AA62: Maximum storage capex that could be deployed this year given scaling constraints. [Current year storage MWh] * [Max annual scaling rate for storage] * [Storage capex per MWh next year]. Represents the upper bound before cash availability is considered.
A63: Max Capex Deployable - Optimus | H63: =(H130*$N$13)*I132 -> 0 | I63: =(I130*$N$13)*J132 -> 51016377 | J63: =(J130*$N$13)*K132 -> 1.4332099e+08 | K63: =(K130*$N$13)*L132 -> 4.0263359e+08 | L63: =(L130*$N$13)*M132 -> 1.131124e+09 | M63: =(M130*$N$13)*N132 -> 3.1776817e+09 | N63: =(N130*$N$13)*O132 -> 8.927104e+09 | O63: =(O130*$N$13)*P132 -> 2.5079033e+10 | ... W63: =(W130*$N$13)*X132 -> 0 | AA63: Maximum Optimus capex that could be deployed this year given scaling constraints. [Current year Optimus units] * [Max annual scaling rate for Optimus] * [Optimus capex per unit next year]. Represents the upper bound before cash availability is considered.
A64: Actual Capex Deployed - Vehicles | H64: =MIN(H61, MAX(0, G$53/(1-$N$15) - SUMIF(H$58:H$60,">"&H58,H$61:H$63))) -> 8.7116875e+09 | I64: =MIN(I61, MAX(0, H$53/(1-$N$15) - SUMIF(I$58:I$60,">"&I58,I$61:I$63))) -> 1.0606402e+10 | J64: =MIN(J61, MAX(0, I$53/(1-$N$15) - SUMIF(J$58:J$60,">"&J58,J$61:J$63))) -> 1.29132e+10 | K64: =MIN(K61, MAX(0, J$53/(1-$N$15) - SUMIF(K$58:K$60,">"&K58,K$61:K$63))) -> 1.5721707e+10 | L64: =MIN(L61, MAX(0, K$53/(1-$N$15) - SUMIF(L$58:L$60,">"&L58,L$61:L$63))) -> 1.9141039e+10 | M64: =MIN(M61, MAX(0, L$53/(1-$N$15) - SUMIF(M$58:M$60,">"&M58,M$61:M$63))) -> 2.3304045e+10 | N64: =MIN(N61, MAX(0, M$53/(1-$N$15) - SUMIF(N$58:N$60,">"&N58,N$61:N$63))) -> 2.8372467e+10 | O64: =MIN(O61, MAX(0, N$53/(1-$N$15) - SUMIF(O$58:O$60,">"&O58,O$61:O$63))) -> 3.4543227e+10 | ... W64: =MIN(W61, MAX(0, V$53/(1-$N$15) - SUMIF(W$58:W$60,">"&W58,W$61:W$63))) -> 0 | AA64: Vehicle capex actually deployed after the cash constraint is applied. Capped by [Max Capex Deployable - Vehicles] and by prior-year [Cash available after AI/fleet reserve] grossed up for the debt-funded portion, after higher-IRR business lines are funded first. Allocation priority is set by ranking the three marginal IRRs. Note on average 2025 capex roughly approximates 2025 actual.
A65: Actual Capex Deployed - Storage | H65: =MIN(H62, MAX(0, G$53/(1-$N$15) - (SUMIF(H$58:H$60,">"&H59,H$61:H$63) + IF(H$58=H59,H$61,0)))) -> 3.2783174e+08 | I65: =MIN(I62, MAX(0, H$53/(1-$N$15) - (SUMIF(I$58:I$60,">"&I59,I$61:I$63) + IF(I$58=I59,I$61,0)))) -> 6.6384753e+08 | J65: =MIN(J62, MAX(0, I$53/(1-$N$15) - (SUMIF(J$58:J$60,">"&J59,J$61:J$63) + IF(J$58=J59,J$61,0)))) -> 1.3442675e+09 | K65: =MIN(K62, MAX(0, J$53/(1-$N$15) - (SUMIF(K$58:K$60,">"&K59,K$61:K$63) + IF(K$58=K59,K$61,0)))) -> 2.7220935e+09 | L65: =MIN(L62, MAX(0, K$53/(1-$N$15) - (SUMIF(L$58:L$60,">"&L59,L$61:L$63) + IF(L$58=L59,L$61,0)))) -> 5.5121418e+09 | M65: =MIN(M62, MAX(0, L$53/(1-$N$15) - (SUMIF(M$58:M$60,">"&M59,M$61:M$63) + IF(M$58=M59,M$61,0)))) -> 1.116189e+10 | N65: =MIN(N62, MAX(0, M$53/(1-$N$15) - (SUMIF(N$58:N$60,">"&N59,N$61:N$63) + IF(N$58=N59,N$61,0)))) -> 2.2602427e+10 | O65: =MIN(O62, MAX(0, N$53/(1-$N$15) - (SUMIF(O$58:O$60,">"&O59,O$61:O$63) + IF(O$58=O59,O$61,0)))) -> 4.5769105e+10 | ... W65: =MIN(W62, MAX(0, V$53/(1-$N$15) - (SUMIF(W$58:W$60,">"&W59,W$61:W$63) + IF(W$58=W59,W$61,0)))) -> 0 | AA65: Storage capex actually deployed after the cash constraint is applied. Capped by [Max Capex Deployable - Storage] and by remaining cash after higher-IRR business lines are funded first. Allocation priority is set by ranking the three marginal IRRs. Note on average 2025 capex roughly approximates 2025 actual.
A66: Actual Capex Deployed - Optimus | H66: =MIN(H63, MAX(0, G$53/(1-$N$15) - (SUMIF(H$58:H$60,">"&H60,H$61:H$63) + IF(H$58=H60,H$61,0) + IF(H$59=H60,H$62,0)))) -> 0 | I66: =MIN(I63, MAX(0, H$53/(1-$N$15) - (SUMIF(I$58:I$60,">"&I60,I$61:I$63) + IF(I$58=I60,I$61,0) + IF(I$59=I60,I$62,0)))) -> 51016377 | J66: =MIN(J63, MAX(0, I$53/(1-$N$15) - (SUMIF(J$58:J$60,">"&J60,J$61:J$63) + IF(J$58=J60,J$61,0) + IF(J$59=J60,J$62,0)))) -> 1.4332099e+08 | K66: =MIN(K63, MAX(0, J$53/(1-$N$15) - (SUMIF(K$58:K$60,">"&K60,K$61:K$63) + IF(K$58=K60,K$61,0) + IF(K$59=K60,K$62,0)))) -> 4.0263359e+08 | L66: =MIN(L63, MAX(0, K$53/(1-$N$15) - (SUMIF(L$58:L$60,">"&L60,L$61:L$63) + IF(L$58=L60,L$61,0) + IF(L$59=L60,L$62,0)))) -> 1.131124e+09 | M66: =MIN(M63, MAX(0, L$53/(1-$N$15) - (SUMIF(M$58:M$60,">"&M60,M$61:M$63) + IF(M$58=M60,M$61,0) + IF(M$59=M60,M$62,0)))) -> 3.1776817e+09 | N66: =MIN(N63, MAX(0, M$53/(1-$N$15) - (SUMIF(N$58:N$60,">"&N60,N$61:N$63) + IF(N$58=N60,N$61,0) + IF(N$59=N60,N$62,0)))) -> 8.927104e+09 | O66: =MIN(O63, MAX(0, N$53/(1-$N$15) - (SUMIF(O$58:O$60,">"&O60,O$61:O$63) + IF(O$58=O60,O$61,0) + IF(O$59=O60,O$62,0)))) -> 2.5079033e+10 | ... W66: =MIN(W63, MAX(0, V$53/(1-$N$15) - (SUMIF(W$58:W$60,">"&W60,W$61:W$63) + IF(W$58=W60,W$61,0) + IF(W$59=W60,W$62,0)))) -> 0 | AA66: Optimus capex actually deployed after the cash constraint is applied. Capped by [Max Capex Deployable - Optimus] and by remaining cash after higher-IRR business lines are funded first. Allocation priority is set by ranking the three marginal IRRs. Note on average 2025 capex roughly approximates 2025 actual.
A67: Actual Capex Deployed - AI Infrastructure & Chip Development | H67: =G50/(1-$N15) -> 0 | I67: =H50/(1-$N15) -> 7.6133865e+09 | J67: =I50/(1-$N15) -> 8.6337101e+09 | K67: =J50/(1-$N15) -> 1.1990119e+10 | L67: =K50/(1-$N15) -> 2.0721608e+10 | M67: =L50/(1-$N15) -> 4.4310422e+10 | N67: =M50/(1-$N15) -> 9.2863365e+10 | O67: =N50/(1-$N15) -> 1.8331845e+11 | ... W67: =V50/(1-$N15) -> 2.1739235e+15 | AA67: AI Infrastructure & Chip Development actual capex spent = prior-year AI cash reserve grossed up for the debt-funded portion: prior-year [AI Infrastructure & Chip Development Cash Allocation] / (1 - [% factory debt-funded]). Flows into AI infrastructure PP&E. Note on average 2025 capex roughly approximates 2025 actual.
A68: PP&E
A69: Gross Property, Plant And Equipment (Vehicles, Stationary Energy Storage & Optimus) | B69: 14130000000 | C69: =17864*10^6 -> 17864000000 | D69: 25615000000 | E69: =32589*10^6 -> 32589000000 | F69: =41782*10^6 -> 41782000000 | G69: =46272*10^6 -> 46272000000 | H69: =54000*10^6 -> 54000000000 | I69: =H69+I64+I65+I66 -> 6.5321266e+10 | J69: =I69+J64+J65+J66 -> 7.9722055e+10 | K69: =J69+K64+K65+K66 -> 9.8568489e+10 | L69: =K69+L64+L65+L66 -> 1.2435279e+11 | M69: =L69+M64+M65+M66 -> 1.6199641e+11 | N69: =M69+N64+N65+N66 -> 2.2189841e+11 | O69: =N69+O64+O65+O66 -> 3.2728977e+11 | P69: =O69+P64+P65+P66 -> 4.3242087e+11 | ... W69: =V69+W64+W65+W66 -> 5.9475323e+13 | AA69: Current year Gross PPE taken from Note 8 in Tesla 10-K. [Previous year's Gross PP&E]+[actual capex deployed by business line].
A70: Gross Property, Plant And Equipment (AI Infrastructure) | B70: 0 | C70: 0 | D70: 0 | E70: 0 | F70: 0 | G70: =5152*10^6 -> 5152000000 | H70: =6816*10^6 -> 6816000000 | I70: =H70+I67 -> 1.4429386e+10 | J70: =I70+J67 -> 2.3063097e+10 | K70: =J70+K67 -> 3.5053215e+10 | L70: =K70+L67 -> 5.5774824e+10 | M70: =L70+M67 -> 1.0008525e+11 | N70: =M70+N67 -> 1.9294861e+11 | O70: =N70+O67 -> 3.7626706e+11 | P70: =O70+P67 -> 1.0957199e+12 | ... W70: =V70+W67 -> 2.8098714e+15 | AA70: [Previous year AI Infra Gross PP&E] + [Actual AI Infrastructure & Chip Development capex this year]. Separated from vehicles/storage/Optimus PP&E because GPUs depreciate faster (~5 yr life).
A71: Gross Cost Of Cumulative Optimi Deployed Internally | B71: 0 | C71: 0 | D71: 0 | E71: 0 | F71: 0 | G71: 0 | H71: 0 | I71: =SUM($B$139:I139) -> 100000000 | J71: =SUM($B$139:J139) -> 3.4462369e+08 | K71: =SUM($B$139:K139) -> 9.7259927e+08 | L71: =SUM($B$139:L139) -> 1.0285093e+09 | M71: =SUM($B$139:M139) -> 1.1740373e+09 | N71: =SUM($B$139:N139) -> 1.5531255e+09 | O71: =SUM($B$139:O139) -> 1.887852e+09 | P71: =SUM($B$139:P139) -> 2.1515772e+09 | ... W71: =SUM($B$139:W139) -> 2.1515772e+09 | AA71: Gross Cost Of Cumulative Optimi Deployed Internally. Assume 2025 Optimus fleet is immaterial.
A72: Gross Cost Of Robotaxi Fleet | B72: 0 | C72: 0 | D72: 0 | E72: 0 | F72: 0 | G72: 0 | H72: 0 | I72: =H72+(I102-H102)*I92 -> 1.1868439e+08 | J72: =I72+(J102-I102)*J92 -> 1.1868439e+08 | K72: =J72+(K102-J102)*K92 -> 1.1868439e+08 | L72: =K72+(L102-K102)*L92 -> 1.1868439e+08 | M72: =L72+(M102-L102)*M92 -> 1.1868439e+08 | N72: =M72+(N102-M102)*N92 -> 1.1868439e+08 | O72: =N72+(O102-N102)*O92 -> 1.1868439e+08 | P72: =O72+(P102-O102)*P92 -> 1.4935074e+08 | ... W72: =V72+(W102-V102)*W92 -> 1.4935074e+08 | AA72: Gross Cost Of Robotaxi Fleet That Tesla Owns. Assume 2025 Robotaxi fleet is immaterial.
A73: Gross Property, Plant And Equipment (Total) | B73: =SUM(B69:B72) -> 14130000000 | C73: =SUM(C69:C72) -> 17864000000 | D73: =SUM(D69:D72) -> 25615000000 | E73: =SUM(E69:E72) -> 32589000000 | F73: =SUM(F69:F72) -> 41782000000 | G73: =SUM(G69:G72) -> 51424000000 | H73: =SUM(H69:H72) -> 60816000000 | I73: =SUM(I69:I72) -> 7.9969337e+10 | ... W73: =SUM(W69:W72) -> 2.8693491e+15 | AA73: [Gross PP&E Vehicles/Storage/Optimus] + [Gross PP&E AI Infrastructure] + [Gross Cost Optimi Deployed Internally] + [Gross Cost Robotaxi Fleet].
A74: Depreciation
A75: Annual Depreciation Vehicles, Stationary Energy Storage & Optimus | B75: 1700000000 | C75: 1570000000 | D75: 1910000000 | E75: 2420000000 | F75: 3330000000 | G75: 4120000000 | H75: 5030000000 | I75: =I69*9% -> 5.8789139e+09 | J75: =J69*9% -> 7.1749849e+09 | K75: =K69*9% -> 8.871164e+09 | L75: =L69*9% -> 1.1191751e+10 | M75: =M69*9% -> 1.4579677e+10 | N75: =N69*9% -> 1.9970857e+10 | O75: =O69*9% -> 2.945608e+10 | P75: =P69*9% -> 3.8917878e+10 | ... W75: =W69*9% -> 5.3527791e+12 | AA75: [Gross PP&E for Vehicles, Stationary Energy Storage & Optimus] * [Depr Rate]. 9% straight-line rate, implying a ~11 year useful life.
A76: Annual Depreciation AI Infrastructure & Chip Development | I76: =I70*16% -> 2.3087018e+09 | J76: =J70*16% -> 3.6900954e+09 | K76: =K70*16% -> 5.6085145e+09 | L76: =L70*16% -> 8.9239718e+09 | M76: =M70*16% -> 1.6013639e+10 | N76: =N70*16% -> 3.0871778e+10 | O76: =O70*16% -> 6.020273e+10 | P76: =P70*16% -> 1.7531518e+11 | ... W76: =W70*16% -> 4.4957943e+14 | AA76: [Gross PP&E for AI Infrastructure] * [AI Infra Depr Rate]. Note 16% is ARK's estimate for weighted average depreciation across an AI facility: accounting for the facility, land etc. at ~14 years and AI Server, Networking etc. at ~5 years.
A77: Annual Depreciation Optimus On Balance Sheet | I77: =I71*9% -> 9000000 | J77: =J71*9% -> 31016132 | K77: =K71*9% -> 87533935 | L77: =L71*9% -> 92565835 | M77: =M71*9% -> 1.0566335e+08 | N77: =N71*9% -> 1.397813e+08 | O77: =O71*9% -> 1.6990668e+08 | P77: =P71*9% -> 1.9364195e+08 | ... W77: =W71*9% -> 1.9364195e+08 | AA77: [Gross Cost Of Cumulative Optimi Deployed Internally] * [Depr Rate]. 9% straight-line rate, implying a ~11 year useful life.
A78: Annual Depreciation Robotaxi On Balance Sheet | I78: =I72*9% -> 10681595 | J78: =J72*9% -> 10681595 | K78: =K72*9% -> 10681595 | L78: =L72*9% -> 10681595 | M78: =M72*9% -> 10681595 | N78: =N72*9% -> 10681595 | O78: =O72*9% -> 10681595 | P78: =P72*9% -> 13441566 | ... W78: =W72*9% -> 13441566 | AA78: [Gross Cost Of Robotaxi Fleet That Tesla Owns] * [Depr Rate]. 9% straight-line rate, implying a ~11 year useful life.
A79: Annual Depreciation | B79: =SUM(B75:B78) -> 1700000000 | C79: =SUM(C75:C78) -> 1570000000 | D79: =SUM(D75:D78) -> 1910000000 | E79: =SUM(E75:E78) -> 2420000000 | F79: =SUM(F75:F78) -> 3330000000 | G79: =SUM(G75:G78) -> 4120000000 | H79: =SUM(H75:H78) -> 5030000000 | I79: =SUM(I75:I78) -> 8.2072974e+09 | ... W79: =SUM(W75:W78) -> 4.5493242e+14 | AA79: [Gross PP&E]*[Depr Rate]
A80: Accumulated Depreciation | B80: =-3734*10^6 -> -3734000000 | C80: =-5117*10^6 -> -5117000000 | D80: =-6731*10^6 -> -6731000000 | E80: =-9041*10^6 -> -9041000000 | F80: =-12057*10^6 -> -12057000000 | G80: =-15588*10^6 -> -15588000000 | H80: =-20173*10^6 -> -20173000000 | I80: =H80-I79 -> -2.8380297e+10 | J80: =I80-J79 -> -3.9287075e+10 | K80: =J80-K79 -> -5.3864969e+10 | L80: =K80-L79 -> -7.408394e+10 | M80: =L80-M79 -> -1.047936e+11 | N80: =M80-N79 -> -1.557867e+11 | O80: =N80-O79 -> -2.456261e+11 | P80: =O80-P79 -> -5.0912901e+11 | ... W80: =V80-W79 -> -5.9918832e+14 | AA80: Cumulative sum of depreciation using Tesla financial statements (Note 8 in 10-k) and Annual Depreciation line
A81: Net Property, Plant And Equipment | B81: =B73+B80 -> 10396000000 | C81: =C73+C80 -> 12747000000 | D81: =D73+D80 -> 18884000000 | E81: =E73+E80 -> 23548000000 | F81: =F73+F80 -> 29725000000 | G81: =G73+G80 -> 35836000000 | H81: =H73+H80 -> 40643000000 | I81: =I73+I80 -> 5.158904e+10 | ... W81: =W73+W80 -> 2.2701607e+15 | AA81: [Gross PP&E]-[Accumulated depreciation]
A82: Debt
A83: Total Long Term Debt | B83: 11700000000 | C83: =9556*10^6 -> 9556000000 | D83: =5245*10^6 -> 5245000000 | E83: =1597*10^6 -> 1597000000 | F83: =2857*10^6 -> 2857000000 | G83: =5757*10^6 -> 5757000000 | H83: =6736*10^6 -> 6736000000 | I83: =H83+((I73-H73)*$N15) -> 9.7718495e+09 | J83: =I83+((J73-I73)*$N15) -> 1.3461646e+10 | K83: =J83+((K73-J73)*$N15) -> 1.8448849e+10 | L83: =K83+((L73-K73)*$N15) -> 2.5829008e+10 | M83: =L83+((M73-L73)*$N15) -> 3.8841985e+10 | N83: =M83+((N73-M73)*$N15) -> 6.3115745e+10 | O83: =N83+((O73-N73)*$N15) -> 1.2022071e+11 | P83: =O83+((P73-O73)*$N15) -> 2.2128824e+11 | ... W83: =V83+((W73-V73)*$N15) -> 4.1889723e+14 | AA83: [Previous years debt] + [percent of Balance sheet debt funded]*([this year's gross PP&E]-[previous year's gross PP&E])
A84: Electric Vehicle | B84: 2019 | C84: =B84+1 -> 2020 | D84: =C84+1 -> 2021 | E84: =D84+1 -> 2022 | F84: =E84+1 -> 2023 | G84: =F84+1 -> 2024 | H84: =G84+1 -> 2025 | I84: =H84+1 -> 2026 | J84: =I84+1 -> 2027 | ... W84: =V84+1 -> 2040
A85: Cars Produceable (Units, Not In Millions) | B85: 365232 | C85: 509737 | D85: 930422 | E85: 1369611 | F85: 1845985 | G85: 1773443 | H85: 1654667 | I85: =MIN(H85+IFERROR(H64/I88,0), H85*(1+$N$10)) -> 2324928.4 | J85: =MIN(I85+IFERROR(I64/J88,0), I85*(1+$N$10)) -> 3266694.7 | K85: =MIN(J85+IFERROR(J64/K88,0), J85*(1+$N$10)) -> 4589945.5 | L85: =MIN(K85+IFERROR(K64/L88,0), K85*(1+$N$10)) -> 6449209.7 | M85: =MIN(L85+IFERROR(L64/M88,0), L85*(1+$N$10)) -> 9061612.2 | N85: =MIN(M85+IFERROR(M64/N88,0), M85*(1+$N$10)) -> 12732229 | O85: =MIN(N85+IFERROR(N64/O88,0), N85*(1+$N$10)) -> 17889715 | P85: =MIN(O85+IFERROR(O64/P88,0), O85*(1+$N$10)) -> 25136360 | ... W85: =MIN(V85+IFERROR(V64/W88,0), V85*(1+$N$10)) -> 2.2728285e+08 | AA85: Assumes Capex committed in the prior year converts into production volume in this year. ([Previous years Capex])/[Capital Efficiency].
A86: Cars Sold | B86: 367500 | C86: 499550 | D86: 936222 | E86: 1313851 | F86: 1808581 | G86: 1789226 | H86: 1636129 | I86: =I85*$N$24 -> 1627449.9 | J86: =J85*$N$24 -> 2286686.3 | K86: =K85*$N$24 -> 3212961.8 | L86: =L85*$N$24 -> 4514446.8 | M86: =M85*$N$24 -> 6343128.6 | N86: =N85*$N$24 -> 8912560.4 | O86: =O85*$N$24 -> 12522800 | P86: =P85*$N$24 -> 16163346 | ... W86: =W85*$N$24 -> 1.6076719e+08 | AA86: [Cars Produceable]*[Factory Utilization Factor]. Relative to Tesla's historical utilization rates.
A87: Cumulative Cars Sold (Modeled Estimate) | B87: 800000 | C87: =B87+C86 -> 1299550 | D87: =C87+D86 -> 2235772 | E87: =D87+E86 -> 3549623 | F87: =E87+F86 -> 5358204 | G87: =F87+G86 -> 7147430 | H87: =G87+H86 -> 8783559 | I87: =H87+I86 -> 10411009 | J87: =I87+J86 -> 12697695 | ... W87: =V87+W86 -> 5.7925772e+08 | AA87: Cumulative Cars Sold
A88: Vehicle Capital Efficiency (Gross Capex Per Vehicle Produced, Not In Millions) | B88: 21000 | C88: 9900 | D88: 7700 | E88: 14800 | F88: 15000 | G88: 15000 | H88: 15000 | I88: =MEDIAN($P$16,H88*(1+_xlfn.RRI(6,$H$88,$N$16)),$R$16) -> 12997.448 | J88: =MEDIAN($P$16,I88*(1+_xlfn.RRI(6,$H$88,$N$16)),$R$16) -> 11262.244 | K88: =MEDIAN($P$16,J88*(1+_xlfn.RRI(6,$H$88,$N$16)),$R$16) -> 9758.6951 | L88: =MEDIAN($P$16,K88*(1+_xlfn.RRI(6,$H$88,$N$16)),$R$16) -> 8455.8754 | M88: =MEDIAN($P$16,L88*(1+_xlfn.RRI(6,$H$88,$N$16)),$R$16) -> 7326.9867 | N88: =MEDIAN($P$16,M88*(1+_xlfn.RRI(6,$H$88,$N$16)),$R$16) -> 6348.8086 | O88: =MEDIAN($P$16,N88*(1+_xlfn.RRI(6,$H$88,$N$16)),$R$16) -> 5501.2207 | P88: =MEDIAN($P$16,O88*(1+_xlfn.RRI(6,$H$88,$N$16)),$R$16) -> 4766.7886 | ... W88: =MEDIAN($P$16,V88*(1+_xlfn.RRI(6,$H$88,$N$16)),$R$16) -> 1800 | AA88: The cost per vehicle of new production capacity. Lower = more efficient
A90: ASP (Not In Millions) | B90: =B91/B86 -> 55039.456 | C90: =C91/C86 -> 51358.222 | D90: =D91/D86 -> 48884.773 | E90: =E91/E86 -> 53039.5 | F90: =F91/F86 -> 44581.36 | G90: =G91/G86 -> 41530.248 | H90: =H91/H86 -> 41276.085 | I90: {=IF(I86=0,0,((I86-IFERROR(INDEX('Valuation ASP Tables'!$E$7:$E$13,MATCH(I86,'Valuation ASP Tables'!$E$7:$E$13,-1)+1),0))*INDEX('Valuation ASP Tables'!$B$7:$B$13,MATCH(I86,'Valuation ASP Tables'!$E$7:$E$13,-1))+IFERROR(INDEX('Valuation ASP Tables'!$G$7:$G$13,MATCH(I86,'Valuation ASP Tables'!$E$7:$E$13,-1)+1),0))/I86)} -> 47919.489 | J90: {=IF(J86=0,0,((J86+'Valuation ASP Tables'!$E$13-INDEX('Valuation ASP Tables'!$E$7:$E$13,MATCH(J86+'Valuation ASP Tables'!$E$13,'Valuation ASP Tables'!$E$7:$E$13,-1)+1))*INDEX('Valuation ASP Tables'!$B$7:$B$13,MATCH(J86+'Valuation ASP Tables'!$E$13,'Valuation ASP Tables'!$E$7:$E$13,-1))+INDEX('Valuation ASP Tables'!$G$7:$G$13,MATCH(J86+'Valuation ASP Tables'!$E$13,'Valuation ASP Tables'!$E$7:$E$13,-1)+1)-'Valuation ASP Tables'!$G$13)/J86)} -> 47917.98 | K90: {=IF(K86=0,0,((K86+'Valuation ASP Tables'!$E$13-INDEX('Valuation ASP Tables'!$E$7:$E$13,MATCH(K86+'Valuation ASP Tables'!$E$13,'Valuation ASP Tables'!$E$7:$E$13,-1)+1))*INDEX('Valuation ASP Tables'!$B$7:$B$13,MATCH(K86+'Valuation ASP Tables'!$E$13,'Valuation ASP Tables'!$E$7:$E$13,-1))+INDEX('Valuation ASP Tables'!$G$7:$G$13,MATCH(K86+'Valuation ASP Tables'!$E$13,'Valuation ASP Tables'!$E$7:$E$13,-1)+1)-'Valuation ASP Tables'!$G$13)/K86)} -> 44316.158 | L90: {=IF(L86=0,0,((L86+'Valuation ASP Tables'!$E$13-INDEX('Valuation ASP Tables'!$E$7:$E$13,MATCH(L86+'Valuation ASP Tables'!$E$13,'Valuation ASP Tables'!$E$7:$E$13,-1)+1))*INDEX('Valuation ASP Tables'!$B$7:$B$13,MATCH(L86+'Valuation ASP Tables'!$E$13,'Valuation ASP Tables'!$E$7:$E$13,-1))+INDEX('Valuation ASP Tables'!$G$7:$G$13,MATCH(L86+'Valuation ASP Tables'!$E$13,'Valuation ASP Tables'!$E$7:$E$13,-1)+1)-'Valuation ASP Tables'!$G$13)/L86)} -> 38747.438 | M90: {=IF(M86=0,0,((M86+'Valuation ASP Tables'!$E$13-INDEX('Valuation ASP Tables'!$E$7:$E$13,MATCH(M86+'Valuation ASP Tables'!$E$13,'Valuation ASP Tables'!$E$7:$E$13,-1)+1))*INDEX('Valuation ASP Tables'!$B$7:$B$13,MATCH(M86+'Valuation ASP Tables'!$E$13,'Valuation ASP Tables'!$E$7:$E$13,-1))+INDEX('Valuation ASP Tables'!$G$7:$G$13,MATCH(M86+'Valuation ASP Tables'!$E$13,'Valuation ASP Tables'!$E$7:$E$13,-1)+1)-'Valuation ASP Tables'!$G$13)/M86)} -> 33201.187 | N90: {=IF(N86=0,0,((N86+'Valuation ASP Tables'!$E$13-INDEX('Valuation ASP Tables'!$E$7:$E$13,MATCH(N86+'Valuation ASP Tables'!$E$13,'Valuation ASP Tables'!$E$7:$E$13,-1)+1))*INDEX('Valuation ASP Tables'!$B$7:$B$13,MATCH(N86+'Valuation ASP Tables'!$E$13,'Valuation ASP Tables'!$E$7:$E$13,-1))+INDEX('Valuation ASP Tables'!$G$7:$G$13,MATCH(N86+'Valuation ASP Tables'!$E$13,'Valuation ASP Tables'!$E$7:$E$13,-1)+1)-'Valuation ASP Tables'!$G$13)/N86)} -> 27953.906 | O90: {=IF(O86=0,0,((O86+'Valuation ASP Tables'!$E$13-INDEX('Valuation ASP Tables'!$E$7:$E$13,MATCH(O86+'Valuation ASP Tables'!$E$13,'Valuation ASP Tables'!$E$7:$E$13,-1)+1))*INDEX('Valuation ASP Tables'!$B$7:$B$13,MATCH(O86+'Valuation ASP Tables'!$E$13,'Valuation ASP Tables'!$E$7:$E$13,-1))+INDEX('Valuation ASP Tables'!$G$7:$G$13,MATCH(O86+'Valuation ASP Tables'!$E$13,'Valuation ASP Tables'!$E$7:$E$13,-1)+1)-'Valuation ASP Tables'!$G$13)/O86)} -> 23975.067 | P90: {=IF(P86=0,0,((P86+'Valuation ASP Tables'!$E$13-INDEX('Valuation ASP Tables'!$E$7:$E$13,MATCH(P86+'Valuation ASP Tables'!$E$13,'Valuation ASP Tables'!$E$7:$E$13,-1)+1))*INDEX('Valuation ASP Tables'!$B$7:$B$13,MATCH(P86+'Valuation ASP Tables'!$E$13,'Valuation ASP Tables'!$E$7:$E$13,-1))+INDEX('Valuation ASP Tables'!$G$7:$G$13,MATCH(P86+'Valuation ASP Tables'!$E$13,'Valuation ASP Tables'!$E$7:$E$13,-1)+1)-'Valuation ASP Tables'!$G$13)/P86)} -> 29613.929 | Q90: {=IF(Q86=0,0,((Q86+'Valuation ASP Tables'!$E$13-INDEX('Valuation ASP Tables'!$E$7:$E$13,MATCH(Q86+'Valuation ASP Tables'!$E$13,'Valuation ASP Tables'!$E$7:$E$13,-1)+1))*INDEX('Valuation ASP Tables'!$B$7:$B$13,MATCH(Q86+'Valuation ASP Tables'!$E$13,'Valuation ASP Tables'!$E$7:$E$13,-1))+INDEX('Valuation ASP Tables'!$G$7:$G$13,MATCH(Q86+'Valuation ASP Tables'!$E$13,'Valuation ASP Tables'!$E$7:$E$13,-1)+1)-'Valuation ASP Tables'!$G$13)/Q86)} -> 25525.512 | ... W90: {=IF(W86=0,0,((W86+'Valuation ASP Tables'!$E$13-INDEX('Valuation ASP Tables'!$E$7:$E$13,MATCH(W86+'Valuation ASP Tables'!$E$13,'Valuation ASP Tables'!$E$7:$E$13,-1)+1))*INDEX('Valuation ASP Tables'!$B$7:$B$13,MATCH(W86+'Valuation ASP Tables'!$E$13,'Valuation ASP Tables'!$E$7:$E$13,-1))+INDEX('Valuation ASP Tables'!$G$7:$G$13,MATCH(W86+'Valuation ASP Tables'!$E$13,'Valuation ASP Tables'!$E$7:$E$13,-1)+1)-'Valuation ASP Tables'!$G$13)/W86)} -> 9705.2696 | AA90: Uses [cars sold] to move down in price within the ASP table. ASP is calculated as if Tesla sells out addressable markets sequentially: first S/X (2026 only; S/X is retired from 2027 onwards and its units and revenue are excluded), then Model 3, then Model Y, then Cybertruck, then Cybercab, with any spillover in Neighborhood EV and Micromobility EV. (The formula takes ASP at the sales volume from the last model-type that they sold out then calculates final ASP by linearly-interpolating ASP between that breakpoint and the next breakpoint in the table.)
A91: Revenue (EV Business Only Ex Credits) | B91: =(20821-594)*10^6 -> 20227000000 | C91: =(27236-1580)*10^6 -> 25656000000 | D91: =(47232-1465)*10^6 -> 45767000000 | E91: =(71462-1776)*10^6 -> 69686000000 | F91: =(82419-1790)*10^6 -> 80629000000 | G91: =(77070-2763)*10^6 -> 74307000000 | H91: =(69526-1993)*10^6 -> 67533000000 | I91: =(I86-(I102-H102))*I90 -> 7.7821575e+10 | J91: =(J86-(J102-I102))*J90 -> 1.0957339e+11 | K91: =(K86-(K102-J102))*K90 -> 1.4238612e+11 | L91: =(L86-(L102-K102))*L90 -> 1.7492325e+11 | M91: =(M86-(M102-L102))*M90 -> 2.105994e+11 | N91: =(N86-(N102-M102))*N90 -> 2.4914088e+11 | O91: =(O86-(O102-N102))*O90 -> 3.0023497e+11 | P91: =(P86-(P102-O102))*P90 -> 4.7866017e+11 | ... W91: =(W86-(W102-V102))*W90 -> 1.5602889e+12 | AA91: EV only! [ASP]*[Cars sold] less Tesla owned robotaxis which go direct into the fleet.
A92: Total COGS Per Vehicle | B92: =B90*(1-B93) -> 44620.408 | C92: =(7070+5506+3862+3821)*10^6/C86 -> 40554.499 | D92: =33393*10^6/D86 -> 35667.822 | E92: =51108*10^6/E86 -> 38899.388 | F92: =66389*10^6/F86 -> 36707.784 | G92: =62873*10^6/G86 -> 35139.776 | H92: =57165*10^6/H86 -> 34939.177 | I92: =MAX($H92*(I87/$H$87)^((LN(1-$N23)/LN(2))),(1-$N22)*I90) -> 34470.128 | J92: =MAX($H92*(J87/$H$87)^((LN(1-$N23)/LN(2))),(1-$N22)*J90) -> 34469.042 | K92: =MAX($H92*(K87/$H$87)^((LN(1-$N23)/LN(2))),(1-$N22)*K90) -> 31878.129 | L92: =MAX($H92*(L87/$H$87)^((LN(1-$N23)/LN(2))),(1-$N22)*L90) -> 28030.628 | M92: =MAX($H92*(M87/$H$87)^((LN(1-$N23)/LN(2))),(1-$N22)*M90) -> 26119.747 | N92: =MAX($H92*(N87/$H$87)^((LN(1-$N23)/LN(2))),(1-$N22)*N90) -> 24231.695 | O92: =MAX($H92*(O87/$H$87)^((LN(1-$N23)/LN(2))),(1-$N22)*O90) -> 22401.473 | P92: =MAX($H92*(P87/$H$87)^((LN(1-$N23)/LN(2))),(1-$N22)*P90) -> 22901.984 | ... W92: =MAX($H92*(W87/$H$87)^((LN(1-$N23)/LN(2))),(1-$N22)*W90) -> 12618.644 | AA92: Max of either: [2025 COGS per vehicle] * ([Cumulative cars sold] / [2025 cumulative]) ^ (LN(1 - Wright's Law learning rate) / LN(2)) — i.e. Wright's Law cost decline driven by cumulative production — OR (1 - [Max gross margin]) * [ASP], which is the COGS floor that prevents gross margin from rising above the max gross margin input.
A93: Gross Margin (Ex Credits) | B93: =(4423-594)*10^6/B91 -> 0.18930143 | C93: =(6977-1580)*10^6/C91 -> 0.21036015 | D93: =(13839-1465)*10^6/D91 -> 0.27036948 | E93: =(20354-1776)*10^6/E91 -> 0.26659587 | F93: =(16030-1790)*10^6/F91 -> 0.17661139 | G93: =(14197-2763)*10^6/G91 -> 0.15387514 | H93: =(12361-1993)*10^6/H91 -> 0.15352494 | I93: =(1-I92/I90) -> 0.28066579 | J93: =(1-J92/J90) -> 0.28066579 | K93: =(1-K92/K90) -> 0.28066579 | L93: =(1-L92/L90) -> 0.27658113 | M93: =(1-M92/M90) -> 0.21328877 | N93: =(1-N92/N90) -> 0.1331553 | O93: =(1-O92/O90) -> 0.065634592 | P93: =(1-P92/P90) -> 0.22664823 | ... W93: =(1-W92/W90) -> -0.30018481 | AA93: 1- [COGS]/[ASP] for future years
A94: Gross Profit | B94: =(B91*B93)+B137 -> 3829000000 | C94: =(C91*C93)+C137 -> 5397000000 | D94: =(D91*D93)+D137 -> 12374000000 | E94: =(E91*E93)+E137 -> 18578000000 | F94: =(F91*F93)+F137 -> 14240000000 | G94: =(G91*G93)+G137 -> 11434000000 | H94: =(H91*H93)+H137 -> 10368000000 | I94: =(I91*I93)+I137 -> 2.1949854e+10 | ... W94: =(W91*W93)+W137 -> -3.6742692e+11 | AA94: [gross margin]*[EV revenue]. Manually add back cost savings from Optimus i.e. assume labor savings impact EV margins only.
A95: EBITDA | D95: =IF(D94<0,D94*(1+$N$28),D94*$N$28) -> 9.601876e+09 | E95: =IF(E94<0,E94*(1+$N$28),E94*$N$28) -> 1.4416006e+10 | F95: =IF(F94<0,F94*(1+$N$28),F94*$N$28) -> 1.104984e+10 | G95: =IF(G94<0,G94*(1+$N$28),G94*$N$28) -> 8.8724625e+09 | H95: =IF(H94<0,H94*(1+$N$28),H94*$N$28) -> 8.0452765e+09 | I95: =IF(I94<0,I94*(1+$N$28),I94*$N$28) -> 1.7032469e+10 | J95: =IF(J94<0,J94*(1+$N$28),J94*$N$28) -> 2.4328258e+10 | K95: =IF(K94<0,K94*(1+$N$28),K94*$N$28) -> 3.2918088e+10 | ... W95: =IF(W94<0,W94*(1+$N$28),W94*$N$28) -> -6.0733908e+11 | AA95: [Gross profit] * [EBITDA % of GM assumed ratio]. If gross profit is negative, apply (1 + [EBITDA % of GM]) so the EBITDA loss scales up rather than shrinking.
A96: EBITDA Margin | D96: =D95/D91 -> 0.20979911 | E96: =E95/E91 -> 0.2068709 | F96: =F95/F91 -> 0.13704547 | G96: =G95/G91 -> 0.11940278 | H96: =H95/H91 -> 0.11913104 | I96: =I95/I91 -> 0.21886565 | J96: =J95/J91 -> 0.22202707 | K96: =K95/K91 -> 0.23118888 | ... W96: =W95/W91 -> -0.38924783 | AA96: [EBITDA EV] / [EV revenue]
A97: Autonomous Ride-hail | B97: 2019 | C97: =B97+1 -> 2020 | D97: =C97+1 -> 2021 | E97: =D97+1 -> 2022 | F97: =E97+1 -> 2023 | G97: =F97+1 -> 2024 | H97: =G97+1 -> 2025 | I97: =H97+1 -> 2026 | J97: =I97+1 -> 2027 | ... W97: =V97+1 -> 2040
A98: Fully Autonomous Capable Fleet (Not In Millions) | F98: 938791 | G98: =F98+AVERAGE(G86,F98) -> 2302799.5 | H98: =G98+AVERAGE(G86:H86) -> 4015477 | I98: =H98+AVERAGE(H86:I86) -> 5647266.4 | J98: =I98+AVERAGE(I86:J86) -> 7604334.5 | K98: =J98+AVERAGE(J86:K86) -> 10354159 | L98: =K98+AVERAGE(K86:L86) -> 14217863 | M98: =L98+AVERAGE(L86:M86) -> 19646651 | N98: =M98+AVERAGE(M86:N86) -> 27274495 | O98: =N98+AVERAGE(N86:O86) -> 37992176 | ... W98: =V98+AVERAGE(V86:W86) -> 4.949241e+08 | AA98: [Cumulative cars sold] from Hardware 4 onwards.
A99: % Of Fleet In China | I99: =$N$33 -> 0.37694604 | J99: =$N$33 -> 0.37694604 | K99: =$N$33 -> 0.37694604 | L99: =$N$33 -> 0.37694604 | M99: =$N$33 -> 0.37694604 | N99: =$N$33 -> 0.37694604 | O99: =$N$33 -> 0.37694604 | P99: =$N$33 -> 0.37694604 | ... W99: =$N$33 -> 0.37694604 | AA99: Input. Share of Tesla's fleet located in China, which is carved out of the autonomous ride-hail business entirely - autonomy runs on the ex-China fleet only.
A100: % Of Teslas On Robotaxi Platform Ex-China | I100: =VLOOKUP((I47-2026),'Valuation ASP Tables'!$A$22:$B$37,2,TRUE) -> 0.0088727235 | J100: =VLOOKUP((J47-2026),'Valuation ASP Tables'!$A$22:$B$37,2,TRUE) -> 0.020306164 | K100: =VLOOKUP((K47-2026),'Valuation ASP Tables'!$A$22:$B$37,2,TRUE) -> 0.045792095 | L100: =VLOOKUP((L47-2026),'Valuation ASP Tables'!$A$22:$B$37,2,TRUE) -> 0.1 | M100: =VLOOKUP((M47-2026),'Valuation ASP Tables'!$A$22:$B$37,2,TRUE) -> 0.20461778 | N100: =VLOOKUP((N47-2026),'Valuation ASP Tables'!$A$22:$B$37,2,TRUE) -> 0.37328878 | O100: =VLOOKUP((O47-2026),'Valuation ASP Tables'!$A$22:$B$37,2,TRUE) -> 0.57966833 | P100: =VLOOKUP((P47-2026),'Valuation ASP Tables'!$A$22:$B$37,2,TRUE) -> 0.76150666 | ... W100: =VLOOKUP((W47-2026),'Valuation ASP Tables'!$A$22:$B$37,2,TRUE) -> 0.99912269 | AA100: Using the autonomous adoption curve from the Valuation ASP Tables sheet
A101: Tesla Robotaxis Cumulative (Not In Millions) | I101: =(I98*(1-I99)*I100) -> 31219.136 | J101: =(J98*(1-J99)*J100) -> 96208.791 | K101: =(K98*(1-K99)*K100) -> 295413.94 | L101: =(L98*(1-L99)*L100) -> 885849.58 | M101: =(M98*(1-M99)*M100) -> 2504710.5 | N101: =(N98*(1-N99)*N100) -> 6343476.2 | O101: =(O98*(1-O99)*O100) -> 13721431 | P101: =(P98*(1-P99)*P100) -> 23556436 | ... W101: =(W98*(1-W99)*W100) -> 3.5004288e+08 | AA101: [fully autonomous capable fleet] * (1 - [% of fleet in China]) * [% of teslas on robotaxi platform ex-China]
...

Sheet Monte Carlo Simulation Output
A1: Monte Carlo Simulation Output
A2: This worksheet contains extracts from all simulations. Note that the workbook may take a minute to calculate.
A3: Note: To utilize the Monte Carlo, you need to use the "Calculate Now" button in excel, not "Calculate Sheet".
A5: Monte Carlo | B5: 2031 Electric Vehicles Sold | C5: 2031 Cumulative Robotaxi Fleet | D5: 2031 Optimus Cumulatively Deployed Externally | E5: 2031 Cumulative Storage Deployed | F5: 2031 Cumulative AI Infrastructure Spend | G5: 2031 Outstanding Debt | H5: 2031 Enterprise Value For Electric Vehicles | I5: 2031 Enterprise Value For Robotaxi | J5: 2031 Enterprise Value For Stationary Energy Storage | K5: 2031 Enterprise Value For External Optimi Sales | L5: 2031 Enterprise Value For Robot-as-a-Service (RaaS) | M5: 2031 Enterprise Value | N5: 2031 Market Cap | O5: 2031 EBITDA Margin | P5: 2031 Gross Margin | Q5: 2031 Share Price | R5: 2031 Optimus Capability (% of Human-Level Productivity)
A6: 1 | B6: ='Monte Carlo Single Simulation'!N86 -> 8912560.4 | C6: ='Monte Carlo Single Simulation'!N101 -> 6343476.2 | D6: ='Monte Carlo Single Simulation'!N142 -> 849214.43 | E6: =SUM('Monte Carlo Single Simulation'!B121:N121) -> 5715458.6 | F6: ='Monte Carlo Single Simulation'!N70 -> 1.9294861e+11 | G6: ='Monte Carlo Single Simulation'!N83 -> 6.3115745e+10 | H6: ='Monte Carlo Single Simulation'!N172 -> 3.2255754e+11 | I6: ='Monte Carlo Single Simulation'!N173 -> 1.2442405e+13 | J6: ='Monte Carlo Single Simulation'!N174 -> 3.4794244e+11 | K6: ='Monte Carlo Single Simulation'!N175 -> 8.6870976e+10 | L6: ='Monte Carlo Single Simulation'!N176 -> 1.7091895e+12 | M6: ='Monte Carlo Single Simulation'!N177 -> 1.4908965e+13 | N6: ='Monte Carlo Single Simulation'!N178 -> 1.5907165e+13 | O6: ='Monte Carlo Single Simulation'!N166 -> 0.61953002 | P6: ='Monte Carlo Single Simulation'!N165 -> 0.67680115 | Q6: ='Monte Carlo Single Simulation'!N180 -> 3923.8198 | R6: ='Monte Carlo Single Simulation'!N136 -> 0.96790757
A7: =A6+1 -> 2 | B7: 12744347 | C7: 11036434 | D7: 841964.9 | E7: 5788644.8 | F7: 2.4686325e+11 | G7: 5.9165017e+10 | H7: 5.9982748e+11 | I7: 1.5741047e+13 | J7: 3.516437e+11 | K7: 8.9675434e+10 | L7: 2.7491009e+12 | M7: 1.9531294e+13 | N7: 2.0859193e+13 | O7: 0.62322869 | P7: 0.68095153 | Q7: 5145.3363 | R7: 1.4786875
A8: =A7+1 -> 3 | B8: 12011879 | C8: 10873714 | D8: 1054542.5 | E8: 4216357.1 | F8: 1.9644453e+11 | G8: 4.7199483e+10 | H8: 7.4499172e+11 | I8: 1.567436e+13 | J8: 1.7959055e+11 | K8: 8.5303716e+10 | L8: 2.8551193e+12 | M8: 1.9539365e+13 | N8: 2.0793766e+13 | O8: 0.64701593 | P8: 0.70855545 | Q8: 5129.1973 | R8: 1.252117
A9: =A8+1 -> 4 | B9: 11824150 | C9: 7317596.9 | D9: 1190277.6 | E9: 4333535 | F9: 1.857411e+11 | G9: 2.9840427e+10 | H9: 6.1262482e+11 | I9: 1.3710769e+13 | J9: 2.669452e+11 | K9: 1.2139076e+11 | L9: 2.9077421e+12 | M9: 1.7619472e+13 | N9: 1.8898784e+13 | O9: 0.63637686 | P9: 0.69644666 | Q9: 4661.7622 | R9: 1.0428604
A10: =A9+1 -> 5 | B10: 10747996 | C10: 9878268.6 | D10: 627462.58 | E10: 4063812.3 | F10: 2.2620551e+11 | G10: 3.9989974e+10 | H10: 6.6993497e+11 | I10: 1.2996553e+13 | J10: 1.9181173e+11 | K10: 1.025849e+11 | L10: 1.6265217e+12 | M10: 1.5587407e+13 | N10: 1.6717499e+13 | O10: 0.62017356 | P10: 0.68696752 | Q10: 4123.7048 | R10: 1.1115112
A11: =A10+1 -> 6 | B11: 12907256 | C11: 11095406 | D11: 851043.64 | E11: 7794969.3 | F11: 2.8579079e+11 | G11: 7.172305e+10 | H11: 6.9712865e+11 | I11: 1.6779538e+13 | J11: 7.2562416e+11 | K11: 1.1205279e+11 | L11: 2.2765743e+12 | M11: 2.0590918e+13 | N11: 2.1882311e+13 | O11: 0.60492864 | P11: 0.66096072 | Q11: 5397.7087 | R11: 1.2740267
A12: =A11+1 -> 7 | B12: 13295256 | C12: 20616062 | D12: 1265377.9 | E12: 4754640.6 | F12: 2.8106955e+11 | G12: 7.4886903e+10 | H12: 6.7650191e+11 | I12: 2.2496691e+13 | J12: 2.8425051e+11 | K12: 7.5418972e+10 | L12: 2.5088547e+12 | M12: 2.6041717e+13 | N12: 2.7551141e+13 | O12: 0.67867602 | P12: 0.75038101 | Q12: 6796.0386 | R12: 1.0711724
A13: =A12+1 -> 8 | B13: 7766040 | C13: 3759831.7 | D13: 1048886.9 | E13: 5774413.4 | F13: 2.2391531e+11 | G13: 4.5069496e+10 | H13: 5.2912975e+11 | I13: 7.7329362e+12 | J13: 3.3550427e+11 | K13: 8.5404481e+10 | L13: 2.1637958e+12 | M13: 1.0846771e+13 | N13: 1.1556377e+13 | O13: 0.52801931 | P13: 0.60001045 | Q13: 2850.611 | R13: 1.0492076
A14: =A13+1 -> 9 | B14: 11381257 | C14: 6399885.7 | D14: 1055425.9 | E14: 4281236.6 | F14: 2.5465364e+11 | G14: 4.9168745e+10 | H14: 5.7418892e+11 | I14: 1.1254871e+13 | J14: 2.6207696e+11 | K14: 7.3524809e+10 | L14: 2.3329048e+12 | M14: 1.4497567e+13 | N14: 1.5455282e+13 | O14: 0.61039055 | P14: 0.67619494 | Q14: 3812.3537 | R14: 1.0015053
A15: =A14+1 -> 10 | B15: 9470905.1 | C15: 6255986.6 | D15: 1599074.5 | E15: 7301098.9 | F15: 2.0889027e+11 | G15: 4.8358476e+10 | H15: 4.503743e+11 | I15: 1.0770212e+13 | J15: 5.836457e+11 | K15: 1.3664235e+11 | L15: 2.7452546e+12 | M15: 1.4686129e+13 | N15: 1.5624641e+13 | O15: 0.563839 | P15: 0.63615049 | Q15: 3854.1296 | R15: 0.89339219
A16: =A15+1 -> 11 | B16: 13892765 | C16: 7241459.7 | D16: 1235083.3 | E16: 4372639.3 | F16: 2.9394527e+11 | G16: 7.9880138e+10 | H16: 5.8400429e+11 | I16: 1.3400633e+13 | J16: 1.3050231e+11 | K16: 1.1068507e+11 | L16: 3.8236623e+12 | M16: 1.8049487e+13 | N16: 1.9190991e+13 | O16: 0.59536704 | P16: 0.67928339 | Q16: 4733.8408 | R16: 1.4919547
A17: =A16+1 -> 12 | B17: 8076797.9 | C17: 10982374 | D17: 719113.49 | E17: 2347167.1 | F17: 2.0018352e+11 | G17: 3.7654843e+10 | H17: 4.5998098e+11 | I17: 1.6851982e+13 | J17: 4.8278578e+10 | K17: 8.6545936e+10 | L17: 1.4578612e+12 | M17: 1.8904648e+13 | N17: 2.0040165e+13 | O17: 0.68380624 | P17: 0.74700343 | Q17: 4943.3067 | R17: 1.0693717
A18: =A17+1 -> 13 | B18: 10381616 | C18: 13295518 | D18: 1245905.6 | E18: 5302413 | F18: 2.4769289e+11 | G18: 4.6824446e+10 | H18: 6.9379967e+11 | I18: 2.0898793e+13 | J18: 3.9272154e+11 | K18: 9.6507412e+10 | L18: 2.7933905e+12 | M18: 2.4875212e+13 | N18: 2.6383973e+13 | O18: 0.67556663 | P18: 0.74106839 | Q18: 6508.1334 | R18: 1.0854725
... A5005: =A5004+1 -> 5000 | B5005: 11261204 | C5005: 4149684.7 | D5005: 870861.17 | E5005: 5621798.9 | F5005: 2.5820657e+11 | G5005: 5.3619857e+10 | H5005: 6.9536791e+11 | I5005: 7.518193e+12 | J5005: 2.6427871e+11 | K5005: 7.6815651e+10 | L5005: 1.5390776e+12 | M5005: 1.0093733e+13 | N5005: 1.0872616e+13 | O5005: 0.50509645 | P5005: 0.57315233 | Q5005: 2681.9477 | R5005: 0.95077812
